<?xml version="1.0" encoding="windows-1252"?>
<XMI xmi.version="1.1" xmlns:UML="omg.org/UML1.3">
	<XMI.header>
		<XMI.documentation>
			<XMI.exporter>Enterprise Architect</XMI.exporter>
			<XMI.exporterVersion>2.5</XMI.exporterVersion>
		</XMI.documentation>
	</XMI.header>
	<XMI.content>
		<UML:Model name="EA Model" xmi.id="MX_EAID_613E819D_CB21_459a_A3AA_EEE9FD2D4B95">
			<UML:Namespace.ownedElement>
				<UML:Class name="EARootClass" xmi.id="EAID_11111111_5487_4080_A7F4_41526CB0AA00" isRoot="true" isLeaf="false" isAbstract="false"/>
				<UML:Package name="Research Questions" xmi.id="EAPK_613E819D_CB21_459a_A3AA_EEE9FD2D4B95" isRoot="false" isLeaf="false" isAbstract="false" visibility="public">
					<UML:ModelElement.taggedValue>
						<UML:TaggedValue tag="parent" value="EAPK_DB25ADF7_72CF_45e9_AB2F_614AE088EE23"/>
						<UML:TaggedValue tag="created" value="2012-09-05 14:48:41"/>
						<UML:TaggedValue tag="modified" value="2012-09-05 14:48:41"/>
						<UML:TaggedValue tag="iscontrolled" value="TRUE"/>
						<UML:TaggedValue tag="xmlpath" value="Evaluations\Research Questions.xml"/>
						<UML:TaggedValue tag="version" value="1.0"/>
						<UML:TaggedValue tag="isprotected" value="FALSE"/>
						<UML:TaggedValue tag="usedtd" value="FALSE"/>
						<UML:TaggedValue tag="owner" value="stalew"/>
						<UML:TaggedValue tag="xmiver" value="Enterprise Architect XMI/UML 1.3"/>
						<UML:TaggedValue tag="logxml" value="FALSE"/>
						<UML:TaggedValue tag="packageFlags" value="Recurse=0;VCCFG=uAAL;CRC=0;"/>
						<UML:TaggedValue tag="batchsave" value="0"/>
						<UML:TaggedValue tag="batchload" value="0"/>
						<UML:TaggedValue tag="phase" value="1.0"/>
						<UML:TaggedValue tag="status" value="Proposed"/>
						<UML:TaggedValue tag="author" value="stalew"/>
						<UML:TaggedValue tag="complexity" value="1"/>
						<UML:TaggedValue tag="ea_stype" value="Public"/>
						<UML:TaggedValue tag="tpos" value="0"/>
						<UML:TaggedValue tag="gentype" value="Java"/>
					</UML:ModelElement.taggedValue>
					<UML:Namespace.ownedElement>
						<UML:Class name="SQR3: Does usability of the whole universAAL platform satisfy the need of having high quality of experience when using AAL systems for all kinds of users?" xmi.id="EAID_3A816B4C_21C4_4eeb_ADC9_2294CA6B460C" visibility="public" namespace="EAPK_613E819D_CB21_459a_A3AA_EEE9FD2D4B95" isRoot="false" isLeaf="false" isAbstract="false" isActive="false">
							<UML:ModelElement.taggedValue>
								<UML:TaggedValue tag="documentation" value="&lt;ul&gt;&#xA;	&lt;li&gt;Are Example Services easily operable by assisted persons? &lt;/li&gt;&#xA;&lt;/ul&gt;"/>
								<UML:TaggedValue tag="isSpecification" value="false"/>
								<UML:TaggedValue tag="ea_stype" value="Class"/>
								<UML:TaggedValue tag="ea_ntype" value="0"/>
								<UML:TaggedValue tag="version" value="1.0"/>
								<UML:TaggedValue tag="package" value="EAPK_613E819D_CB21_459a_A3AA_EEE9FD2D4B95"/>
								<UML:TaggedValue tag="date_created" value="2012-09-05 15:05:04"/>
								<UML:TaggedValue tag="date_modified" value="2012-09-05 15:05:40"/>
								<UML:TaggedValue tag="gentype" value="Java"/>
								<UML:TaggedValue tag="tagged" value="0"/>
								<UML:TaggedValue tag="package_name" value="Research Questions"/>
								<UML:TaggedValue tag="phase" value="1.0"/>
								<UML:TaggedValue tag="author" value="stalew"/>
								<UML:TaggedValue tag="complexity" value="1"/>
								<UML:TaggedValue tag="status" value="Proposed"/>
								<UML:TaggedValue tag="tpos" value="0"/>
								<UML:TaggedValue tag="ea_localid" value="15871"/>
								<UML:TaggedValue tag="ea_eleType" value="element"/>
								<UML:TaggedValue tag="style" value="BackColor=-1;BorderColor=-1;BorderWidth=-1;FontColor=-1;VSwimLanes=1;HSwimLanes=1;BorderStyle=0;"/>
							</UML:ModelElement.taggedValue>
						</UML:Class>
						<UML:Class name="SQR5: Does the uStore" xmi.id="EAID_4F5A93F4_B06F_4809_9604_53C4EF8A0307" visibility="public" namespace="EAPK_613E819D_CB21_459a_A3AA_EEE9FD2D4B95" isRoot="false" isLeaf="false" isAbstract="false" isActive="false">
							<UML:ModelElement.taggedValue>
								<UML:TaggedValue tag="documentation" value="&lt;ul&gt;&#xA;	&lt;li&gt;allow easy interaction among stakeholders?&lt;/li&gt;&#xA;	&lt;li&gt;search for, request, purchase, download, install and use universAAL based services?&lt;/li&gt;&#xA;&lt;/ul&gt;&#xA;&#xA;"/>
								<UML:TaggedValue tag="isSpecification" value="false"/>
								<UML:TaggedValue tag="ea_stype" value="Class"/>
								<UML:TaggedValue tag="ea_ntype" value="0"/>
								<UML:TaggedValue tag="version" value="1.0"/>
								<UML:TaggedValue tag="package" value="EAPK_613E819D_CB21_459a_A3AA_EEE9FD2D4B95"/>
								<UML:TaggedValue tag="date_created" value="2012-09-05 15:08:45"/>
								<UML:TaggedValue tag="date_modified" value="2012-09-05 15:09:08"/>
								<UML:TaggedValue tag="gentype" value="Java"/>
								<UML:TaggedValue tag="tagged" value="0"/>
								<UML:TaggedValue tag="package_name" value="Research Questions"/>
								<UML:TaggedValue tag="phase" value="1.0"/>
								<UML:TaggedValue tag="author" value="stalew"/>
								<UML:TaggedValue tag="complexity" value="1"/>
								<UML:TaggedValue tag="status" value="Proposed"/>
								<UML:TaggedValue tag="tpos" value="0"/>
								<UML:TaggedValue tag="ea_localid" value="15873"/>
								<UML:TaggedValue tag="ea_eleType" value="element"/>
								<UML:TaggedValue tag="style" value="BackColor=-1;BorderColor=-1;BorderWidth=-1;FontColor=-1;VSwimLanes=1;HSwimLanes=1;BorderStyle=0;"/>
							</UML:ModelElement.taggedValue>
						</UML:Class>
						<UML:Class name="SQR2: Does productivity of Development Support and Community Support allow creating cost-effective services" xmi.id="EAID_5972CDCF_8235_4841_98EB_1D466C2E2FAF" visibility="public" namespace="EAPK_613E819D_CB21_459a_A3AA_EEE9FD2D4B95" isRoot="false" isLeaf="false" isAbstract="false" isActive="false">
							<UML:ModelElement.taggedValue>
								<UML:TaggedValue tag="isSpecification" value="false"/>
								<UML:TaggedValue tag="ea_stype" value="Class"/>
								<UML:TaggedValue tag="ea_ntype" value="0"/>
								<UML:TaggedValue tag="version" value="1.0"/>
								<UML:TaggedValue tag="package" value="EAPK_613E819D_CB21_459a_A3AA_EEE9FD2D4B95"/>
								<UML:TaggedValue tag="date_created" value="2012-09-05 15:04:24"/>
								<UML:TaggedValue tag="date_modified" value="2012-09-05 15:04:44"/>
								<UML:TaggedValue tag="gentype" value="Java"/>
								<UML:TaggedValue tag="tagged" value="0"/>
								<UML:TaggedValue tag="package_name" value="Research Questions"/>
								<UML:TaggedValue tag="phase" value="1.0"/>
								<UML:TaggedValue tag="author" value="stalew"/>
								<UML:TaggedValue tag="complexity" value="1"/>
								<UML:TaggedValue tag="status" value="Proposed"/>
								<UML:TaggedValue tag="tpos" value="0"/>
								<UML:TaggedValue tag="ea_localid" value="15870"/>
								<UML:TaggedValue tag="ea_eleType" value="element"/>
								<UML:TaggedValue tag="style" value="BackColor=-1;BorderColor=-1;BorderWidth=-1;FontColor=-1;VSwimLanes=1;HSwimLanes=1;BorderStyle=0;"/>
							</UML:ModelElement.taggedValue>
						</UML:Class>
						<UML:Class name="SQR10: Does the Community Support give sufficient support for training and help for non-technical users?" xmi.id="EAID_612D9BB5_8F68_42ac_818B_F61BD0C08057" visibility="public" namespace="EAPK_613E819D_CB21_459a_A3AA_EEE9FD2D4B95" isRoot="false" isLeaf="false" isAbstract="false" isActive="false">
							<UML:ModelElement.taggedValue>
								<UML:TaggedValue tag="isSpecification" value="false"/>
								<UML:TaggedValue tag="ea_stype" value="Class"/>
								<UML:TaggedValue tag="ea_ntype" value="0"/>
								<UML:TaggedValue tag="version" value="1.0"/>
								<UML:TaggedValue tag="package" value="EAPK_613E819D_CB21_459a_A3AA_EEE9FD2D4B95"/>
								<UML:TaggedValue tag="date_created" value="2012-09-05 15:13:58"/>
								<UML:TaggedValue tag="date_modified" value="2012-09-05 15:14:19"/>
								<UML:TaggedValue tag="gentype" value="Java"/>
								<UML:TaggedValue tag="tagged" value="0"/>
								<UML:TaggedValue tag="package_name" value="Research Questions"/>
								<UML:TaggedValue tag="phase" value="1.0"/>
								<UML:TaggedValue tag="author" value="stalew"/>
								<UML:TaggedValue tag="complexity" value="1"/>
								<UML:TaggedValue tag="status" value="Proposed"/>
								<UML:TaggedValue tag="tpos" value="0"/>
								<UML:TaggedValue tag="ea_localid" value="15878"/>
								<UML:TaggedValue tag="ea_eleType" value="element"/>
								<UML:TaggedValue tag="style" value="BackColor=-1;BorderColor=-1;BorderWidth=-1;FontColor=-1;VSwimLanes=1;HSwimLanes=1;BorderStyle=0;"/>
							</UML:ModelElement.taggedValue>
						</UML:Class>
						<UML:Class name="SQR4: Do Example Services allow assisted persons to:" xmi.id="EAID_79E37D9F_8AC1_4e6f_8F9A_BF517CF2DA3B" visibility="public" namespace="EAPK_613E819D_CB21_459a_A3AA_EEE9FD2D4B95" isRoot="false" isLeaf="false" isAbstract="false" isActive="false">
							<UML:ModelElement.taggedValue>
								<UML:TaggedValue tag="documentation" value="&lt;ul&gt;&#xA;	&lt;li&gt;not to feel alone?&lt;/li&gt;&#xA;	&lt;li&gt;have a personalised interaction?&lt;/li&gt;&#xA;	&lt;li&gt;not impose changes in life?&lt;/li&gt;&#xA;&lt;/ul&gt;"/>
								<UML:TaggedValue tag="isSpecification" value="false"/>
								<UML:TaggedValue tag="ea_stype" value="Class"/>
								<UML:TaggedValue tag="ea_ntype" value="0"/>
								<UML:TaggedValue tag="version" value="1.0"/>
								<UML:TaggedValue tag="package" value="EAPK_613E819D_CB21_459a_A3AA_EEE9FD2D4B95"/>
								<UML:TaggedValue tag="date_created" value="2012-09-05 15:08:27"/>
								<UML:TaggedValue tag="date_modified" value="2012-09-05 15:08:42"/>
								<UML:TaggedValue tag="gentype" value="Java"/>
								<UML:TaggedValue tag="tagged" value="0"/>
								<UML:TaggedValue tag="package_name" value="Research Questions"/>
								<UML:TaggedValue tag="phase" value="1.0"/>
								<UML:TaggedValue tag="author" value="stalew"/>
								<UML:TaggedValue tag="complexity" value="1"/>
								<UML:TaggedValue tag="status" value="Proposed"/>
								<UML:TaggedValue tag="tpos" value="0"/>
								<UML:TaggedValue tag="ea_localid" value="15872"/>
								<UML:TaggedValue tag="ea_eleType" value="element"/>
								<UML:TaggedValue tag="style" value="BackColor=-1;BorderColor=-1;BorderWidth=-1;FontColor=-1;VSwimLanes=1;HSwimLanes=1;BorderStyle=0;"/>
							</UML:ModelElement.taggedValue>
						</UML:Class>
						<UML:Class name="SQR11: Does the resource utilization of the Runtime Support and the Example Services allow creating energy efficient systems?" xmi.id="EAID_9D30A241_6C25_4245_953B_310BA4614B75" visibility="public" namespace="EAPK_613E819D_CB21_459a_A3AA_EEE9FD2D4B95" isRoot="false" isLeaf="false" isAbstract="false" isActive="false">
							<UML:ModelElement.taggedValue>
								<UML:TaggedValue tag="isSpecification" value="false"/>
								<UML:TaggedValue tag="ea_stype" value="Class"/>
								<UML:TaggedValue tag="ea_ntype" value="0"/>
								<UML:TaggedValue tag="version" value="1.0"/>
								<UML:TaggedValue tag="package" value="EAPK_613E819D_CB21_459a_A3AA_EEE9FD2D4B95"/>
								<UML:TaggedValue tag="date_created" value="2012-09-05 15:14:46"/>
								<UML:TaggedValue tag="date_modified" value="2012-09-05 15:14:54"/>
								<UML:TaggedValue tag="gentype" value="Java"/>
								<UML:TaggedValue tag="tagged" value="0"/>
								<UML:TaggedValue tag="package_name" value="Research Questions"/>
								<UML:TaggedValue tag="phase" value="1.0"/>
								<UML:TaggedValue tag="author" value="stalew"/>
								<UML:TaggedValue tag="complexity" value="1"/>
								<UML:TaggedValue tag="status" value="Proposed"/>
								<UML:TaggedValue tag="tpos" value="0"/>
								<UML:TaggedValue tag="ea_localid" value="15879"/>
								<UML:TaggedValue tag="ea_eleType" value="element"/>
								<UML:TaggedValue tag="style" value="BackColor=-1;BorderColor=-1;BorderWidth=-1;FontColor=-1;VSwimLanes=1;HSwimLanes=1;BorderStyle=0;"/>
							</UML:ModelElement.taggedValue>
						</UML:Class>
						<UML:Class name="SQR6: Do the interoperability and portability of the universAAL platform allow the creation of interoperable services running on multiple hardware and software platforms?" xmi.id="EAID_AC23A312_F414_4dbd_9854_8C28EF4CE271" visibility="public" namespace="EAPK_613E819D_CB21_459a_A3AA_EEE9FD2D4B95" isRoot="false" isLeaf="false" isAbstract="false" isActive="false">
							<UML:ModelElement.taggedValue>
								<UML:TaggedValue tag="documentation" value="&lt;ul&gt;&#xA;	&lt;li&gt;Do they provide support for deployment and testing on divergent hardware and different environments?&lt;/li&gt;&#xA;&lt;/ul&gt;"/>
								<UML:TaggedValue tag="isSpecification" value="false"/>
								<UML:TaggedValue tag="ea_stype" value="Class"/>
								<UML:TaggedValue tag="ea_ntype" value="0"/>
								<UML:TaggedValue tag="version" value="1.0"/>
								<UML:TaggedValue tag="package" value="EAPK_613E819D_CB21_459a_A3AA_EEE9FD2D4B95"/>
								<UML:TaggedValue tag="date_created" value="2012-09-05 15:09:09"/>
								<UML:TaggedValue tag="date_modified" value="2012-09-05 15:09:30"/>
								<UML:TaggedValue tag="gentype" value="Java"/>
								<UML:TaggedValue tag="tagged" value="0"/>
								<UML:TaggedValue tag="package_name" value="Research Questions"/>
								<UML:TaggedValue tag="phase" value="1.0"/>
								<UML:TaggedValue tag="author" value="stalew"/>
								<UML:TaggedValue tag="complexity" value="1"/>
								<UML:TaggedValue tag="status" value="Proposed"/>
								<UML:TaggedValue tag="tpos" value="0"/>
								<UML:TaggedValue tag="ea_localid" value="15874"/>
								<UML:TaggedValue tag="ea_eleType" value="element"/>
								<UML:TaggedValue tag="style" value="BackColor=-1;BorderColor=-1;BorderWidth=-1;FontColor=-1;VSwimLanes=1;HSwimLanes=1;BorderStyle=0;"/>
							</UML:ModelElement.taggedValue>
						</UML:Class>
						<UML:Class name="SQR7: Do Runtime Support and Development Support developers in" xmi.id="EAID_ADF823AE_EE9B_4d37_AF02_E7122F625C63" visibility="public" namespace="EAPK_613E819D_CB21_459a_A3AA_EEE9FD2D4B95" isRoot="false" isLeaf="false" isAbstract="false" isActive="false">
							<UML:ModelElement.taggedValue>
								<UML:TaggedValue tag="documentation" value="&lt;ul&gt;&#xA;	&lt;li&gt;documenting code and trace design?&lt;/li&gt;&#xA;	&lt;li&gt;decoupling and reuse of open components?&lt;/li&gt;&#xA;	&lt;li&gt;applying domain standards, reference design and programming patterns?&lt;/li&gt;&#xA;&lt;/ul&gt;"/>
								<UML:TaggedValue tag="isSpecification" value="false"/>
								<UML:TaggedValue tag="ea_stype" value="Class"/>
								<UML:TaggedValue tag="ea_ntype" value="0"/>
								<UML:TaggedValue tag="version" value="1.0"/>
								<UML:TaggedValue tag="package" value="EAPK_613E819D_CB21_459a_A3AA_EEE9FD2D4B95"/>
								<UML:TaggedValue tag="date_created" value="2012-09-05 15:13:03"/>
								<UML:TaggedValue tag="date_modified" value="2012-09-05 15:13:18"/>
								<UML:TaggedValue tag="gentype" value="Java"/>
								<UML:TaggedValue tag="tagged" value="0"/>
								<UML:TaggedValue tag="package_name" value="Research Questions"/>
								<UML:TaggedValue tag="phase" value="1.0"/>
								<UML:TaggedValue tag="author" value="stalew"/>
								<UML:TaggedValue tag="complexity" value="1"/>
								<UML:TaggedValue tag="status" value="Proposed"/>
								<UML:TaggedValue tag="tpos" value="0"/>
								<UML:TaggedValue tag="ea_localid" value="15875"/>
								<UML:TaggedValue tag="ea_eleType" value="element"/>
								<UML:TaggedValue tag="style" value="BackColor=-1;BorderColor=-1;BorderWidth=-1;FontColor=-1;VSwimLanes=1;HSwimLanes=1;BorderStyle=0;"/>
							</UML:ModelElement.taggedValue>
						</UML:Class>
						<UML:Class name="SQR8: Does Development Support learnability make it easy to learn universAAL?" xmi.id="EAID_AF22A4E4_0B66_4468_9507_9A97BDB0EFA1" visibility="public" namespace="EAPK_613E819D_CB21_459a_A3AA_EEE9FD2D4B95" isRoot="false" isLeaf="false" isAbstract="false" isActive="false">
							<UML:ModelElement.taggedValue>
								<UML:TaggedValue tag="isSpecification" value="false"/>
								<UML:TaggedValue tag="ea_stype" value="Class"/>
								<UML:TaggedValue tag="ea_ntype" value="0"/>
								<UML:TaggedValue tag="version" value="1.0"/>
								<UML:TaggedValue tag="package" value="EAPK_613E819D_CB21_459a_A3AA_EEE9FD2D4B95"/>
								<UML:TaggedValue tag="date_created" value="2012-09-05 15:13:19"/>
								<UML:TaggedValue tag="date_modified" value="2012-09-05 15:13:32"/>
								<UML:TaggedValue tag="gentype" value="Java"/>
								<UML:TaggedValue tag="tagged" value="0"/>
								<UML:TaggedValue tag="package_name" value="Research Questions"/>
								<UML:TaggedValue tag="phase" value="1.0"/>
								<UML:TaggedValue tag="author" value="stalew"/>
								<UML:TaggedValue tag="complexity" value="1"/>
								<UML:TaggedValue tag="status" value="Proposed"/>
								<UML:TaggedValue tag="tpos" value="0"/>
								<UML:TaggedValue tag="ea_localid" value="15876"/>
								<UML:TaggedValue tag="ea_eleType" value="element"/>
								<UML:TaggedValue tag="style" value="BackColor=-1;BorderColor=-1;BorderWidth=-1;FontColor=-1;VSwimLanes=1;HSwimLanes=1;BorderStyle=0;"/>
							</UML:ModelElement.taggedValue>
						</UML:Class>
						<UML:Class name="SQR9: Is the Runtime Support enough installable and testable so that it is easy to deploy and monitor services?" xmi.id="EAID_D33B4C8D_651D_4aa8_86C3_9D90ECE4EC26" visibility="public" namespace="EAPK_613E819D_CB21_459a_A3AA_EEE9FD2D4B95" isRoot="false" isLeaf="false" isAbstract="false" isActive="false">
							<UML:ModelElement.taggedValue>
								<UML:TaggedValue tag="isSpecification" value="false"/>
								<UML:TaggedValue tag="ea_stype" value="Class"/>
								<UML:TaggedValue tag="ea_ntype" value="0"/>
								<UML:TaggedValue tag="version" value="1.0"/>
								<UML:TaggedValue tag="package" value="EAPK_613E819D_CB21_459a_A3AA_EEE9FD2D4B95"/>
								<UML:TaggedValue tag="date_created" value="2012-09-05 15:13:34"/>
								<UML:TaggedValue tag="date_modified" value="2012-09-05 15:13:56"/>
								<UML:TaggedValue tag="gentype" value="Java"/>
								<UML:TaggedValue tag="tagged" value="0"/>
								<UML:TaggedValue tag="package_name" value="Research Questions"/>
								<UML:TaggedValue tag="phase" value="1.0"/>
								<UML:TaggedValue tag="author" value="stalew"/>
								<UML:TaggedValue tag="complexity" value="1"/>
								<UML:TaggedValue tag="status" value="Proposed"/>
								<UML:TaggedValue tag="tpos" value="0"/>
								<UML:TaggedValue tag="ea_localid" value="15877"/>
								<UML:TaggedValue tag="ea_eleType" value="element"/>
								<UML:TaggedValue tag="style" value="BackColor=-1;BorderColor=-1;BorderWidth=-1;FontColor=-1;VSwimLanes=1;HSwimLanes=1;BorderStyle=0;"/>
							</UML:ModelElement.taggedValue>
						</UML:Class>
						<UML:Class name="SQR1: Do the security and safety of the whole platform allow developing applications that are compatible with norms and regulations" xmi.id="EAID_DFF8D015_8BFA_43a6_BA6F_DFCDEB75F017" visibility="public" namespace="EAPK_613E819D_CB21_459a_A3AA_EEE9FD2D4B95" isRoot="false" isLeaf="false" isAbstract="false" isActive="false">
							<UML:ModelElement.taggedValue>
								<UML:TaggedValue tag="documentation" value="&lt;ul&gt;&#xA;	&lt;li&gt;Do they provide secure communication, data storage and access control means?&lt;/li&gt;&#xA;	&lt;li&gt;Do they facilitate understanding how responsibilities of formal caregivers are shared?&lt;/li&gt;&#xA;&lt;/ul&gt;"/>
								<UML:TaggedValue tag="isSpecification" value="false"/>
								<UML:TaggedValue tag="ea_stype" value="Class"/>
								<UML:TaggedValue tag="ea_ntype" value="0"/>
								<UML:TaggedValue tag="version" value="1.0"/>
								<UML:TaggedValue tag="package" value="EAPK_613E819D_CB21_459a_A3AA_EEE9FD2D4B95"/>
								<UML:TaggedValue tag="date_created" value="2012-09-05 15:04:02"/>
								<UML:TaggedValue tag="date_modified" value="2012-09-05 15:04:58"/>
								<UML:TaggedValue tag="gentype" value="Java"/>
								<UML:TaggedValue tag="tagged" value="0"/>
								<UML:TaggedValue tag="package_name" value="Research Questions"/>
								<UML:TaggedValue tag="phase" value="1.0"/>
								<UML:TaggedValue tag="author" value="stalew"/>
								<UML:TaggedValue tag="complexity" value="1"/>
								<UML:TaggedValue tag="status" value="Proposed"/>
								<UML:TaggedValue tag="tpos" value="0"/>
								<UML:TaggedValue tag="ea_localid" value="15869"/>
								<UML:TaggedValue tag="ea_eleType" value="element"/>
								<UML:TaggedValue tag="style" value="BackColor=-1;BorderColor=-1;BorderWidth=-1;FontColor=-1;VSwimLanes=1;HSwimLanes=1;BorderStyle=0;"/>
							</UML:ModelElement.taggedValue>
						</UML:Class>
					</UML:Namespace.ownedElement>
				</UML:Package>
			</UML:Namespace.ownedElement>
		</UML:Model>
		<UML:Diagram name="Research Questions" xmi.id="EAID_67AF9126_0F66_4f4b_B032_8AA8125EDFD2" diagramType="ClassDiagram" owner="EAPK_613E819D_CB21_459a_A3AA_EEE9FD2D4B95" toolName="Enterprise Architect 2.5">
			<UML:ModelElement.taggedValue>
				<UML:TaggedValue tag="version" value="1.0"/>
				<UML:TaggedValue tag="author" value="stalew"/>
				<UML:TaggedValue tag="created_date" value="2012-09-05 14:48:48"/>
				<UML:TaggedValue tag="modified_date" value="2012-09-05 15:21:07"/>
				<UML:TaggedValue tag="package" value="EAPK_613E819D_CB21_459a_A3AA_EEE9FD2D4B95"/>
				<UML:TaggedValue tag="type" value="Logical"/>
				<UML:TaggedValue tag="swimlanes" value="locked=false;orientation=0;width=0;inbar=false;names=false;color=0;bold=false;fcol=0;;cls=0;"/>
				<UML:TaggedValue tag="matrixitems" value="locked=false;matrixactive=false;swimlanesactive=true;width=1;"/>
				<UML:TaggedValue tag="ea_localid" value="1711"/>
				<UML:TaggedValue tag="EAStyle" value="ShowPrivate=1;ShowProtected=1;ShowPublic=1;HideRelationships=0;Locked=0;Border=1;HighlightForeign=1;PackageContents=1;SequenceNotes=0;ScalePrintImage=0;PPgs.cx=2;PPgs.cy=1;DocSize.cx=815;DocSize.cy=1063;ShowDetails=0;Orientation=P;Zoom=100;ShowTags=0;OpParams=1;VisibleAttributeDetail=0;ShowOpRetType=1;ShowIcons=1;CollabNums=0;HideProps=0;ShowReqs=0;ShowCons=0;PaperSize=1;HideParents=0;UseAlias=0;HideAtts=0;HideOps=0;HideStereo=0;HideElemStereo=0;ShowTests=0;ShowMaint=0;ConnectorNotation=UML 2.1;ExplicitNavigability=0;AdvancedElementProps=1;AdvancedFeatureProps=1;AdvancedConnectorProps=1;ShowNotes=0;SuppressBrackets=0;SuppConnectorLabels=0;PrintPageHeadFoot=0;ShowAsList=0;HideConnStereotype=0;ShowFQN=0;NoFullScope=0;"/>
				<UML:TaggedValue tag="styleex" value="SaveTag=86404360;ExcludeRTF=0;DocAll=0;HideQuals=0;AttPkg=1;ShowTests=0;ShowMaint=0;SuppressFOC=1;MatrixActive=0;SwimlanesActive=1;MatrixLineWidth=1;MatrixLocked=0;TConnectorNotation=UML 2.1;TExplicitNavigability=0;AdvancedElementProps=1;AdvancedFeatureProps=1;AdvancedConnectorProps=1;ProfileData=;MDGDgm=;DefaultLang=;STBLDgm=;ShowNotes=0;VisibleAttributeDetail=0;ShowOpRetType=1;SuppressBrackets=0;SuppConnectorLabels=0;PrintPageHeadFoot=0;ShowAsList=0;OverrideLinkedF=0;HideConnStereotype=0;ShowFQN=0;NoFullScope=0;"/>
			</UML:ModelElement.taggedValue>
			<UML:Diagram.element>
				<UML:DiagramElement geometry="Left=734;Top=470;Right=868;Bottom=730;" subject="EAID_9D30A241_6C25_4245_953B_310BA4614B75" seqno="1" style="DUID=46B92405;AttCustom=0;OpCustom=0;Notes=1000;RzO=1;"/>
				<UML:DiagramElement geometry="Left=595;Top=470;Right=715;Bottom=730;" subject="EAID_612D9BB5_8F68_42ac_818B_F61BD0C08057" seqno="2" style="DUID=DA673E42;AttCustom=0;OpCustom=0;Notes=1000;RzO=1;"/>
				<UML:DiagramElement geometry="Left=453;Top=470;Right=583;Bottom=730;" subject="EAID_D33B4C8D_651D_4aa8_86C3_9D90ECE4EC26" seqno="3" style="DUID=BD4C5B04;AttCustom=0;OpCustom=0;Notes=1000;RzO=1;"/>
				<UML:DiagramElement geometry="Left=321;Top=470;Right=441;Bottom=730;" subject="EAID_AF22A4E4_0B66_4468_9507_9A97BDB0EFA1" seqno="4" style="DUID=524EA3A1;AttCustom=0;OpCustom=0;Notes=1000;RzO=1;"/>
				<UML:DiagramElement geometry="Left=180;Top=470;Right=309;Bottom=777;" subject="EAID_ADF823AE_EE9B_4d37_AF02_E7122F625C63" seqno="5" style="DUID=FD0EF6F4;AttCustom=0;OpCustom=0;Notes=1000;RzO=1;"/>
				<UML:DiagramElement geometry="Left=48;Top=470;Right=168;Bottom=822;" subject="EAID_AC23A312_F414_4dbd_9854_8C28EF4CE271" seqno="6" style="DUID=A6E54500;AttCustom=0;OpCustom=0;Notes=1000;RzO=1;"/>
				<UML:DiagramElement geometry="Left=688;Top=101;Right=808;Bottom=361;" subject="EAID_4F5A93F4_B06F_4809_9604_53C4EF8A0307" seqno="7" style="DUID=CB7E08D1;AttCustom=0;OpCustom=0;Notes=1000;RzO=1;"/>
				<UML:DiagramElement geometry="Left=551;Top=101;Right=683;Bottom=361;" subject="EAID_79E37D9F_8AC1_4e6f_8F9A_BF517CF2DA3B" seqno="8" style="DUID=1C25A90D;AttCustom=0;OpCustom=0;Notes=1000;RzO=1;"/>
				<UML:DiagramElement geometry="Left=403;Top=101;Right=546;Bottom=361;" subject="EAID_3A816B4C_21C4_4eeb_ADC9_2294CA6B460C" seqno="9" style="DUID=7E7899BC;AttCustom=0;OpCustom=0;Notes=1000;RzO=1;"/>
				<UML:DiagramElement geometry="Left=278;Top=101;Right=398;Bottom=361;" subject="EAID_5972CDCF_8235_4841_98EB_1D466C2E2FAF" seqno="10" style="DUID=80D7673E;AttCustom=0;OpCustom=0;Notes=1000;RzO=1;"/>
				<UML:DiagramElement geometry="Left=131;Top=101;Right=273;Bottom=423;" subject="EAID_DFF8D015_8BFA_43a6_BA6F_DFCDEB75F017" seqno="11" style="DUID=8C1FE390;AttCustom=0;OpCustom=0;Notes=1000;RzO=1;"/>
			</UML:Diagram.element>
		</UML:Diagram>
	</XMI.content>
	<XMI.difference/>
	<XMI.extensions xmi.extender="Enterprise Architect 2.5"/>
</XMI>
