<?xml version="1.0" encoding="windows-1252"?>
<XMI xmi.version="1.1" xmlns:UML="omg.org/UML1.3">
	<XMI.header>
		<XMI.documentation>
			<XMI.exporter>Enterprise Architect</XMI.exporter>
			<XMI.exporterVersion>2.5</XMI.exporterVersion>
		</XMI.documentation>
	</XMI.header>
	<XMI.content>
		<UML:Model name="EA Model" xmi.id="MX_EAID_4DB1BF9B_A889_4442_BBDF_E0632A20E77C">
			<UML:Namespace.ownedElement>
				<UML:Class name="EARootClass" xmi.id="EAID_11111111_5487_4080_A7F4_41526CB0AA00" isRoot="true" isLeaf="false" isAbstract="false"/>
				<UML:Package name="ont.MedMgr" xmi.id="EAPK_4DB1BF9B_A889_4442_BBDF_E0632A20E77C" isRoot="false" isLeaf="false" isAbstract="false" visibility="public">
					<UML:ModelElement.taggedValue>
						<UML:TaggedValue tag="parent" value="EAPK_3702F345_DD07_4b74_B03F_A05A62DEFDD1"/>
						<UML:TaggedValue tag="created" value="2012-01-27 14:49:00"/>
						<UML:TaggedValue tag="modified" value="2012-01-27 14:49:00"/>
						<UML:TaggedValue tag="iscontrolled" value="TRUE"/>
						<UML:TaggedValue tag="xmlpath" value="eaE\E0632A20E77C.xml"/>
						<UML:TaggedValue tag="version" value="1.0"/>
						<UML:TaggedValue tag="isprotected" value="FALSE"/>
						<UML:TaggedValue tag="usedtd" value="FALSE"/>
						<UML:TaggedValue tag="logxml" value="FALSE"/>
						<UML:TaggedValue tag="packageFlags" value="VCCFG=uAAL;CRC=0;"/>
						<UML:TaggedValue tag="phase" value="1.0"/>
						<UML:TaggedValue tag="status" value="Proposed"/>
						<UML:TaggedValue tag="author" value="Venelin"/>
						<UML:TaggedValue tag="complexity" value="1"/>
						<UML:TaggedValue tag="ea_stype" value="Public"/>
						<UML:TaggedValue tag="tpos" value="0"/>
						<UML:TaggedValue tag="gentype" value="Java"/>
					</UML:ModelElement.taggedValue>
					<UML:Namespace.ownedElement>
						<UML:Class name="MedTreatment" xmi.id="EAID_07A78DEC_947E_4ba1_9743_E9A32521B4C8" visibility="public" namespace="EAPK_4DB1BF9B_A889_4442_BBDF_E0632A20E77C" isRoot="false" isLeaf="false" isAbstract="false" isActive="false">
							<UML:ModelElement.taggedValue>
								<UML:TaggedValue tag="isSpecification" value="false"/>
								<UML:TaggedValue tag="ea_stype" value="Class"/>
								<UML:TaggedValue tag="ea_ntype" value="0"/>
								<UML:TaggedValue tag="version" value="1.0"/>
								<UML:TaggedValue tag="package" value="EAPK_4DB1BF9B_A889_4442_BBDF_E0632A20E77C"/>
								<UML:TaggedValue tag="date_created" value="2012-01-27 14:56:09"/>
								<UML:TaggedValue tag="date_modified" value="2012-02-01 15:26:39"/>
								<UML:TaggedValue tag="gentype" value="Java"/>
								<UML:TaggedValue tag="tagged" value="0"/>
								<UML:TaggedValue tag="package_name" value="ont.MedMgr"/>
								<UML:TaggedValue tag="phase" value="1.0"/>
								<UML:TaggedValue tag="author" value="Venelin"/>
								<UML:TaggedValue tag="complexity" value="1"/>
								<UML:TaggedValue tag="status" value="Proposed"/>
								<UML:TaggedValue tag="tpos" value="0"/>
								<UML:TaggedValue tag="ea_localid" value="7462"/>
								<UML:TaggedValue tag="ea_eleType" value="element"/>
								<UML:TaggedValue tag="style" value="BackColor=-1;BorderColor=-1;BorderWidth=-1;FontColor=-1;VSwimLanes=1;HSwimLanes=1;BorderStyle=0;"/>
							</UML:ModelElement.taggedValue>
						</UML:Class>
						<UML:Association name="hasPrecaution" xmi.id="EAID_3B315DD9_BBA8_4b3e_A2B7_9C4C530D7D44" visibility="public" isRoot="false" isLeaf="false" isAbstract="false">
							<UML:ModelElement.taggedValue>
								<UML:TaggedValue tag="style" value="3"/>
								<UML:TaggedValue tag="ea_type" value="Aggregation"/>
								<UML:TaggedValue tag="direction" value="Source -&gt; Destination"/>
								<UML:TaggedValue tag="linemode" value="3"/>
								<UML:TaggedValue tag="linecolor" value="-1"/>
								<UML:TaggedValue tag="linewidth" value="0"/>
								<UML:TaggedValue tag="seqno" value="0"/>
								<UML:TaggedValue tag="subtype" value="Weak"/>
								<UML:TaggedValue tag="headStyle" value="0"/>
								<UML:TaggedValue tag="lineStyle" value="0"/>
								<UML:TaggedValue tag="ea_localid" value="6498"/>
								<UML:TaggedValue tag="ea_sourceName" value="Precaution"/>
								<UML:TaggedValue tag="ea_targetName" value="MedTreatment"/>
								<UML:TaggedValue tag="ea_sourceType" value="Class"/>
								<UML:TaggedValue tag="ea_targetType" value="Class"/>
								<UML:TaggedValue tag="ea_sourceID" value="7468"/>
								<UML:TaggedValue tag="ea_targetID" value="7462"/>
								<UML:TaggedValue tag="virtualInheritance" value="0"/>
								<UML:TaggedValue tag="lb" value="1"/>
								<UML:TaggedValue tag="mt" value="hasPrecaution"/>
							</UML:ModelElement.taggedValue>
							<UML:Association.connection>
								<UML:AssociationEnd visibility="public" multiplicity="1" aggregation="none" isOrdered="false" targetScope="instance" changeable="none" isNavigable="false" type="EAID_7609610B_51A5_4b72_B7DD_DF4E35D63C6B">
									<UML:ModelElement.taggedValue>
										<UML:TaggedValue tag="containment" value="Unspecified"/>
										<UML:TaggedValue tag="sourcestyle" value="Union=0;Derived=0;AllowDuplicates=0;Owned=0;Navigable=Non-Navigable;"/>
										<UML:TaggedValue tag="ea_end" value="source"/>
									</UML:ModelElement.taggedValue>
								</UML:AssociationEnd>
								<UML:AssociationEnd visibility="public" aggregation="shared" isOrdered="false" targetScope="instance" changeable="none" isNavigable="true" type="EAID_07A78DEC_947E_4ba1_9743_E9A32521B4C8">
									<UML:ModelElement.taggedValue>
										<UML:TaggedValue tag="containment" value="Unspecified"/>
										<UML:TaggedValue tag="deststyle" value="Union=0;Derived=0;AllowDuplicates=0;Owned=0;Navigable=Navigable;"/>
										<UML:TaggedValue tag="ea_end" value="target"/>
									</UML:ModelElement.taggedValue>
								</UML:AssociationEnd>
							</UML:Association.connection>
						</UML:Association>
						<UML:Association name="hasPrescriptions" xmi.id="EAID_AA3427EF_C860_41b3_830C_97A0EDA98B63" visibility="public" isRoot="false" isLeaf="false" isAbstract="false">
							<UML:ModelElement.taggedValue>
								<UML:TaggedValue tag="style" value="3"/>
								<UML:TaggedValue tag="ea_type" value="Aggregation"/>
								<UML:TaggedValue tag="direction" value="Source -&gt; Destination"/>
								<UML:TaggedValue tag="linemode" value="3"/>
								<UML:TaggedValue tag="linecolor" value="-1"/>
								<UML:TaggedValue tag="linewidth" value="0"/>
								<UML:TaggedValue tag="seqno" value="0"/>
								<UML:TaggedValue tag="subtype" value="Weak"/>
								<UML:TaggedValue tag="headStyle" value="0"/>
								<UML:TaggedValue tag="lineStyle" value="0"/>
								<UML:TaggedValue tag="ea_localid" value="6497"/>
								<UML:TaggedValue tag="ea_sourceName" value="Prescription"/>
								<UML:TaggedValue tag="ea_targetName" value="MedTreatment"/>
								<UML:TaggedValue tag="ea_sourceType" value="Class"/>
								<UML:TaggedValue tag="ea_targetType" value="Class"/>
								<UML:TaggedValue tag="ea_sourceID" value="7466"/>
								<UML:TaggedValue tag="ea_targetID" value="7462"/>
								<UML:TaggedValue tag="virtualInheritance" value="0"/>
								<UML:TaggedValue tag="lb" value="0..*"/>
								<UML:TaggedValue tag="mt" value="hasPrescriptions"/>
							</UML:ModelElement.taggedValue>
							<UML:Association.connection>
								<UML:AssociationEnd visibility="public" multiplicity="0..*" aggregation="none" isOrdered="false" targetScope="instance" changeable="none" isNavigable="false" type="EAID_A043C0B5_1FD9_4a44_B5E0_4D9DFCBF4549">
									<UML:ModelElement.taggedValue>
										<UML:TaggedValue tag="containment" value="Unspecified"/>
										<UML:TaggedValue tag="sourcestyle" value="Union=0;Derived=0;AllowDuplicates=0;Owned=0;Navigable=Non-Navigable;"/>
										<UML:TaggedValue tag="ea_end" value="source"/>
									</UML:ModelElement.taggedValue>
								</UML:AssociationEnd>
								<UML:AssociationEnd visibility="public" aggregation="shared" isOrdered="false" targetScope="instance" changeable="none" isNavigable="true" type="EAID_07A78DEC_947E_4ba1_9743_E9A32521B4C8">
									<UML:ModelElement.taggedValue>
										<UML:TaggedValue tag="containment" value="Unspecified"/>
										<UML:TaggedValue tag="deststyle" value="Union=0;Derived=0;AllowDuplicates=0;Owned=0;Navigable=Navigable;"/>
										<UML:TaggedValue tag="ea_end" value="target"/>
									</UML:ModelElement.taggedValue>
								</UML:AssociationEnd>
							</UML:Association.connection>
						</UML:Association>
						<UML:Association name="hasIntakes" xmi.id="EAID_FD5AD238_8F8B_4e62_A206_1E7967D3FFB4" visibility="public" isRoot="false" isLeaf="false" isAbstract="false">
							<UML:ModelElement.taggedValue>
								<UML:TaggedValue tag="style" value="3"/>
								<UML:TaggedValue tag="ea_type" value="Aggregation"/>
								<UML:TaggedValue tag="direction" value="Source -&gt; Destination"/>
								<UML:TaggedValue tag="linemode" value="3"/>
								<UML:TaggedValue tag="linecolor" value="-1"/>
								<UML:TaggedValue tag="linewidth" value="0"/>
								<UML:TaggedValue tag="seqno" value="0"/>
								<UML:TaggedValue tag="subtype" value="Weak"/>
								<UML:TaggedValue tag="headStyle" value="0"/>
								<UML:TaggedValue tag="lineStyle" value="0"/>
								<UML:TaggedValue tag="ea_localid" value="6503"/>
								<UML:TaggedValue tag="ea_sourceName" value="Intake"/>
								<UML:TaggedValue tag="ea_targetName" value="MedTreatment"/>
								<UML:TaggedValue tag="ea_sourceType" value="Class"/>
								<UML:TaggedValue tag="ea_targetType" value="Class"/>
								<UML:TaggedValue tag="ea_sourceID" value="7465"/>
								<UML:TaggedValue tag="ea_targetID" value="7462"/>
								<UML:TaggedValue tag="virtualInheritance" value="0"/>
								<UML:TaggedValue tag="lb" value="0..*"/>
								<UML:TaggedValue tag="mt" value="hasIntakes"/>
							</UML:ModelElement.taggedValue>
							<UML:Association.connection>
								<UML:AssociationEnd visibility="public" multiplicity="0..*" aggregation="none" isOrdered="false" targetScope="instance" changeable="none" isNavigable="false" type="EAID_D6D1CDC5_3805_4209_BFDB_E29147C7C283">
									<UML:ModelElement.taggedValue>
										<UML:TaggedValue tag="containment" value="Unspecified"/>
										<UML:TaggedValue tag="sourcestyle" value="Union=0;Derived=0;AllowDuplicates=0;Owned=0;Navigable=Non-Navigable;"/>
										<UML:TaggedValue tag="ea_end" value="source"/>
									</UML:ModelElement.taggedValue>
								</UML:AssociationEnd>
								<UML:AssociationEnd visibility="public" aggregation="shared" isOrdered="false" targetScope="instance" changeable="none" isNavigable="true" type="EAID_07A78DEC_947E_4ba1_9743_E9A32521B4C8">
									<UML:ModelElement.taggedValue>
										<UML:TaggedValue tag="containment" value="Unspecified"/>
										<UML:TaggedValue tag="deststyle" value="Union=0;Derived=0;AllowDuplicates=0;Owned=0;Navigable=Navigable;"/>
										<UML:TaggedValue tag="ea_end" value="target"/>
									</UML:ModelElement.taggedValue>
								</UML:AssociationEnd>
							</UML:Association.connection>
						</UML:Association>
						<UML:Class name="IntakeDose" xmi.id="EAID_221369A4_8050_4b68_A7F0_9431AB359338" visibility="public" namespace="EAPK_4DB1BF9B_A889_4442_BBDF_E0632A20E77C" isRoot="false" isLeaf="false" isAbstract="false" isActive="false">
							<UML:ModelElement.taggedValue>
								<UML:TaggedValue tag="documentation" value="What the patient is going to take. Could be different from the PrescribedDose as far:&#xA;- The medicine purchased is not identical to the prescribed one, but equivalent, so there is a difference of the names although the same ingredients and effect&#xA;- The IntakeTime is more specific as compared with the general Frequency "/>
								<UML:TaggedValue tag="isSpecification" value="false"/>
								<UML:TaggedValue tag="ea_stype" value="Class"/>
								<UML:TaggedValue tag="ea_ntype" value="0"/>
								<UML:TaggedValue tag="version" value="1.0"/>
								<UML:TaggedValue tag="package" value="EAPK_4DB1BF9B_A889_4442_BBDF_E0632A20E77C"/>
								<UML:TaggedValue tag="date_created" value="2012-01-27 15:46:13"/>
								<UML:TaggedValue tag="date_modified" value="2012-02-01 15:28:10"/>
								<UML:TaggedValue tag="gentype" value="Java"/>
								<UML:TaggedValue tag="tagged" value="0"/>
								<UML:TaggedValue tag="package_name" value="ont.MedMgr"/>
								<UML:TaggedValue tag="phase" value="1.0"/>
								<UML:TaggedValue tag="author" value="Venelin"/>
								<UML:TaggedValue tag="complexity" value="1"/>
								<UML:TaggedValue tag="status" value="Proposed"/>
								<UML:TaggedValue tag="tpos" value="0"/>
								<UML:TaggedValue tag="ea_localid" value="7469"/>
								<UML:TaggedValue tag="ea_eleType" value="element"/>
								<UML:TaggedValue tag="style" value="BackColor=-1;BorderColor=-1;BorderWidth=-1;FontColor=-1;VSwimLanes=1;HSwimLanes=1;BorderStyle=0;"/>
							</UML:ModelElement.taggedValue>
							<UML:Classifier.feature>
								<UML:Attribute name="DoseQty" changeable="none" visibility="private" ownerScope="instance" targetScope="instance">
									<UML:Attribute.initialValue>
										<UML:Expression/>
									</UML:Attribute.initialValue>
									<UML:StructuralFeature.type>
										<UML:Classifier xmi.idref="eaxmiid0"/>
									</UML:StructuralFeature.type>
									<UML:ModelElement.taggedValue>
										<UML:TaggedValue tag="description" value="as in PrescribedDose"/>
										<UML:TaggedValue tag="type" value="int"/>
										<UML:TaggedValue tag="derived" value="0"/>
										<UML:TaggedValue tag="containment" value="Not Specified"/>
										<UML:TaggedValue tag="ordered" value="0"/>
										<UML:TaggedValue tag="collection" value="false"/>
										<UML:TaggedValue tag="position" value="0"/>
										<UML:TaggedValue tag="lowerBound" value="1"/>
										<UML:TaggedValue tag="upperBound" value="1"/>
										<UML:TaggedValue tag="duplicates" value="0"/>
										<UML:TaggedValue tag="ea_guid" value="{10A5A550-26D3-4cc7-BC28-7FA4EF91B437}"/>
										<UML:TaggedValue tag="ea_localid" value="1925"/>
										<UML:TaggedValue tag="styleex" value="IsLiteral=0;volatile=0;"/>
									</UML:ModelElement.taggedValue>
								</UML:Attribute>
								<UML:Attribute name="DoseUnit" changeable="none" visibility="private" ownerScope="instance" targetScope="instance">
									<UML:Attribute.initialValue>
										<UML:Expression/>
									</UML:Attribute.initialValue>
									<UML:StructuralFeature.type>
										<UML:Classifier xmi.idref="eaxmiid1"/>
									</UML:StructuralFeature.type>
									<UML:ModelElement.taggedValue>
										<UML:TaggedValue tag="description" value="as in PrescribedDose"/>
										<UML:TaggedValue tag="type" value="char"/>
										<UML:TaggedValue tag="derived" value="0"/>
										<UML:TaggedValue tag="containment" value="Not Specified"/>
										<UML:TaggedValue tag="ordered" value="0"/>
										<UML:TaggedValue tag="collection" value="false"/>
										<UML:TaggedValue tag="position" value="1"/>
										<UML:TaggedValue tag="lowerBound" value="1"/>
										<UML:TaggedValue tag="upperBound" value="1"/>
										<UML:TaggedValue tag="duplicates" value="0"/>
										<UML:TaggedValue tag="ea_guid" value="{B26E4E52-9E39-4959-8EA3-BABA7499311B}"/>
										<UML:TaggedValue tag="ea_localid" value="1926"/>
										<UML:TaggedValue tag="styleex" value="IsLiteral=0;volatile=0;"/>
									</UML:ModelElement.taggedValue>
								</UML:Attribute>
							</UML:Classifier.feature>
						</UML:Class>
						<UML:Association name="hasIntakeMedicine" xmi.id="EAID_03DE4CCF_482E_40ff_AEC5_20C0E762F233" visibility="public" isRoot="false" isLeaf="false" isAbstract="false">
							<UML:ModelElement.taggedValue>
								<UML:TaggedValue tag="style" value="3"/>
								<UML:TaggedValue tag="ea_type" value="Aggregation"/>
								<UML:TaggedValue tag="direction" value="Source -&gt; Destination"/>
								<UML:TaggedValue tag="linemode" value="3"/>
								<UML:TaggedValue tag="linecolor" value="-1"/>
								<UML:TaggedValue tag="linewidth" value="0"/>
								<UML:TaggedValue tag="seqno" value="0"/>
								<UML:TaggedValue tag="subtype" value="Weak"/>
								<UML:TaggedValue tag="headStyle" value="0"/>
								<UML:TaggedValue tag="lineStyle" value="0"/>
								<UML:TaggedValue tag="ea_localid" value="6502"/>
								<UML:TaggedValue tag="ea_sourceName" value="IntakeMedicine"/>
								<UML:TaggedValue tag="ea_targetName" value="IntakeDose"/>
								<UML:TaggedValue tag="ea_sourceType" value="Class"/>
								<UML:TaggedValue tag="ea_targetType" value="Class"/>
								<UML:TaggedValue tag="ea_sourceID" value="7470"/>
								<UML:TaggedValue tag="ea_targetID" value="7469"/>
								<UML:TaggedValue tag="virtualInheritance" value="0"/>
								<UML:TaggedValue tag="lb" value="1"/>
								<UML:TaggedValue tag="mt" value="hasIntakeMedicine"/>
							</UML:ModelElement.taggedValue>
							<UML:Association.connection>
								<UML:AssociationEnd visibility="public" multiplicity="1" aggregation="none" isOrdered="false" targetScope="instance" changeable="none" isNavigable="false" type="EAID_CB5BDDFF_8D6E_44c1_9D57_CE51478C1DA9">
									<UML:ModelElement.taggedValue>
										<UML:TaggedValue tag="containment" value="Unspecified"/>
										<UML:TaggedValue tag="sourcestyle" value="Union=0;Derived=0;AllowDuplicates=0;Owned=0;Navigable=Non-Navigable;"/>
										<UML:TaggedValue tag="ea_end" value="source"/>
									</UML:ModelElement.taggedValue>
								</UML:AssociationEnd>
								<UML:AssociationEnd visibility="public" aggregation="shared" isOrdered="false" targetScope="instance" changeable="none" isNavigable="true" type="EAID_221369A4_8050_4b68_A7F0_9431AB359338">
									<UML:ModelElement.taggedValue>
										<UML:TaggedValue tag="containment" value="Unspecified"/>
										<UML:TaggedValue tag="deststyle" value="Union=0;Derived=0;AllowDuplicates=0;Owned=0;Navigable=Navigable;"/>
										<UML:TaggedValue tag="ea_end" value="target"/>
									</UML:ModelElement.taggedValue>
								</UML:AssociationEnd>
							</UML:Association.connection>
						</UML:Association>
						<UML:Association name="hasIntakeDose" xmi.id="EAID_905A7C67_88A0_43d3_BD7B_CEB2D162BB90" visibility="public" isRoot="false" isLeaf="false" isAbstract="false">
							<UML:ModelElement.taggedValue>
								<UML:TaggedValue tag="style" value="3"/>
								<UML:TaggedValue tag="ea_type" value="Aggregation"/>
								<UML:TaggedValue tag="direction" value="Source -&gt; Destination"/>
								<UML:TaggedValue tag="linemode" value="3"/>
								<UML:TaggedValue tag="linecolor" value="-1"/>
								<UML:TaggedValue tag="linewidth" value="0"/>
								<UML:TaggedValue tag="seqno" value="0"/>
								<UML:TaggedValue tag="subtype" value="Weak"/>
								<UML:TaggedValue tag="headStyle" value="0"/>
								<UML:TaggedValue tag="lineStyle" value="0"/>
								<UML:TaggedValue tag="ea_localid" value="6501"/>
								<UML:TaggedValue tag="ea_sourceName" value="IntakeDose"/>
								<UML:TaggedValue tag="ea_targetName" value="Intake"/>
								<UML:TaggedValue tag="ea_sourceType" value="Class"/>
								<UML:TaggedValue tag="ea_targetType" value="Class"/>
								<UML:TaggedValue tag="ea_sourceID" value="7469"/>
								<UML:TaggedValue tag="ea_targetID" value="7465"/>
								<UML:TaggedValue tag="virtualInheritance" value="0"/>
								<UML:TaggedValue tag="lb" value="1..*"/>
								<UML:TaggedValue tag="mt" value="hasIntakeDose"/>
							</UML:ModelElement.taggedValue>
							<UML:Association.connection>
								<UML:AssociationEnd visibility="public" multiplicity="1..*" aggregation="none" isOrdered="false" targetScope="instance" changeable="none" isNavigable="false" type="EAID_221369A4_8050_4b68_A7F0_9431AB359338">
									<UML:ModelElement.taggedValue>
										<UML:TaggedValue tag="containment" value="Unspecified"/>
										<UML:TaggedValue tag="sourcestyle" value="Union=0;Derived=0;AllowDuplicates=0;Owned=0;Navigable=Non-Navigable;"/>
										<UML:TaggedValue tag="ea_end" value="source"/>
									</UML:ModelElement.taggedValue>
								</UML:AssociationEnd>
								<UML:AssociationEnd visibility="public" aggregation="shared" isOrdered="false" targetScope="instance" changeable="none" isNavigable="true" type="EAID_D6D1CDC5_3805_4209_BFDB_E29147C7C283">
									<UML:ModelElement.taggedValue>
										<UML:TaggedValue tag="containment" value="Unspecified"/>
										<UML:TaggedValue tag="deststyle" value="Union=0;Derived=0;AllowDuplicates=0;Owned=0;Navigable=Navigable;"/>
										<UML:TaggedValue tag="ea_end" value="target"/>
									</UML:ModelElement.taggedValue>
								</UML:AssociationEnd>
							</UML:Association.connection>
						</UML:Association>
						<UML:Class name="PrescribedDose" xmi.id="EAID_2FF07B53_DA18_4ab5_AAA5_BE8949C44933" visibility="public" namespace="EAPK_4DB1BF9B_A889_4442_BBDF_E0632A20E77C" isRoot="false" isLeaf="false" isAbstract="false" isActive="false">
							<UML:ModelElement.taggedValue>
								<UML:TaggedValue tag="isSpecification" value="false"/>
								<UML:TaggedValue tag="ea_stype" value="Class"/>
								<UML:TaggedValue tag="ea_ntype" value="0"/>
								<UML:TaggedValue tag="version" value="1.0"/>
								<UML:TaggedValue tag="package" value="EAPK_4DB1BF9B_A889_4442_BBDF_E0632A20E77C"/>
								<UML:TaggedValue tag="date_created" value="2012-01-27 15:28:29"/>
								<UML:TaggedValue tag="date_modified" value="2012-01-27 15:43:28"/>
								<UML:TaggedValue tag="gentype" value="Java"/>
								<UML:TaggedValue tag="tagged" value="0"/>
								<UML:TaggedValue tag="package_name" value="ont.MedMgr"/>
								<UML:TaggedValue tag="phase" value="1.0"/>
								<UML:TaggedValue tag="author" value="Venelin"/>
								<UML:TaggedValue tag="complexity" value="1"/>
								<UML:TaggedValue tag="status" value="Proposed"/>
								<UML:TaggedValue tag="tpos" value="0"/>
								<UML:TaggedValue tag="ea_localid" value="7467"/>
								<UML:TaggedValue tag="ea_eleType" value="element"/>
								<UML:TaggedValue tag="style" value="BackColor=-1;BorderColor=-1;BorderWidth=-1;FontColor=-1;VSwimLanes=1;HSwimLanes=1;BorderStyle=0;"/>
							</UML:ModelElement.taggedValue>
							<UML:Classifier.feature>
								<UML:Attribute name="DoseQty" changeable="none" visibility="private" ownerScope="instance" targetScope="instance">
									<UML:Attribute.initialValue>
										<UML:Expression/>
									</UML:Attribute.initialValue>
									<UML:StructuralFeature.type>
										<UML:Classifier xmi.idref="eaxmiid0"/>
									</UML:StructuralFeature.type>
									<UML:ModelElement.taggedValue>
										<UML:TaggedValue tag="description" value="The amount of medicine to be taken"/>
										<UML:TaggedValue tag="type" value="int"/>
										<UML:TaggedValue tag="derived" value="0"/>
										<UML:TaggedValue tag="containment" value="Not Specified"/>
										<UML:TaggedValue tag="ordered" value="0"/>
										<UML:TaggedValue tag="collection" value="false"/>
										<UML:TaggedValue tag="position" value="0"/>
										<UML:TaggedValue tag="lowerBound" value="1"/>
										<UML:TaggedValue tag="upperBound" value="1"/>
										<UML:TaggedValue tag="duplicates" value="0"/>
										<UML:TaggedValue tag="ea_guid" value="{78B3179B-7AAF-4398-A612-7DE1D10DC815}"/>
										<UML:TaggedValue tag="ea_localid" value="1917"/>
										<UML:TaggedValue tag="styleex" value="IsLiteral=0;volatile=0;"/>
									</UML:ModelElement.taggedValue>
								</UML:Attribute>
								<UML:Attribute name="DoseUnit" changeable="none" visibility="private" ownerScope="instance" targetScope="instance">
									<UML:Attribute.initialValue>
										<UML:Expression/>
									</UML:Attribute.initialValue>
									<UML:StructuralFeature.type>
										<UML:Classifier xmi.idref="eaxmiid1"/>
									</UML:StructuralFeature.type>
									<UML:ModelElement.taggedValue>
										<UML:TaggedValue tag="description" value="Units of the dose (ml, pill...)"/>
										<UML:TaggedValue tag="type" value="char"/>
										<UML:TaggedValue tag="derived" value="0"/>
										<UML:TaggedValue tag="containment" value="Not Specified"/>
										<UML:TaggedValue tag="ordered" value="0"/>
										<UML:TaggedValue tag="collection" value="false"/>
										<UML:TaggedValue tag="position" value="1"/>
										<UML:TaggedValue tag="lowerBound" value="1"/>
										<UML:TaggedValue tag="upperBound" value="1"/>
										<UML:TaggedValue tag="duplicates" value="0"/>
										<UML:TaggedValue tag="ea_guid" value="{1FFB60C7-39D9-4fce-AFD6-520993166977}"/>
										<UML:TaggedValue tag="ea_localid" value="1918"/>
										<UML:TaggedValue tag="styleex" value="IsLiteral=0;volatile=0;"/>
									</UML:ModelElement.taggedValue>
								</UML:Attribute>
								<UML:Attribute name="Frequency" changeable="none" visibility="private" ownerScope="instance" targetScope="instance">
									<UML:Attribute.initialValue>
										<UML:Expression/>
									</UML:Attribute.initialValue>
									<UML:StructuralFeature.type>
										<UML:Classifier xmi.idref="eaxmiid1"/>
									</UML:StructuralFeature.type>
									<UML:ModelElement.taggedValue>
										<UML:TaggedValue tag="description" value="Verbose description of how often the dose should be taken (once a day, 3 times before meal, ...) &#xA;optional"/>
										<UML:TaggedValue tag="type" value="char"/>
										<UML:TaggedValue tag="derived" value="0"/>
										<UML:TaggedValue tag="containment" value="Not Specified"/>
										<UML:TaggedValue tag="ordered" value="0"/>
										<UML:TaggedValue tag="collection" value="false"/>
										<UML:TaggedValue tag="position" value="2"/>
										<UML:TaggedValue tag="lowerBound" value="1"/>
										<UML:TaggedValue tag="upperBound" value="1"/>
										<UML:TaggedValue tag="duplicates" value="0"/>
										<UML:TaggedValue tag="ea_guid" value="{AFC02692-BDC4-4d30-8C8C-918B45742BD5}"/>
										<UML:TaggedValue tag="ea_localid" value="1919"/>
										<UML:TaggedValue tag="styleex" value="IsLiteral=0;volatile=0;"/>
									</UML:ModelElement.taggedValue>
								</UML:Attribute>
							</UML:Classifier.feature>
						</UML:Class>
						<UML:Association name="hasMedicine" xmi.id="EAID_56689A4B_2F1D_4206_BF9B_F318948A3CE1" visibility="public" isRoot="false" isLeaf="false" isAbstract="false">
							<UML:ModelElement.taggedValue>
								<UML:TaggedValue tag="style" value="3"/>
								<UML:TaggedValue tag="ea_type" value="Aggregation"/>
								<UML:TaggedValue tag="direction" value="Source -&gt; Destination"/>
								<UML:TaggedValue tag="linemode" value="3"/>
								<UML:TaggedValue tag="linecolor" value="-1"/>
								<UML:TaggedValue tag="linewidth" value="0"/>
								<UML:TaggedValue tag="seqno" value="0"/>
								<UML:TaggedValue tag="subtype" value="Weak"/>
								<UML:TaggedValue tag="headStyle" value="0"/>
								<UML:TaggedValue tag="lineStyle" value="0"/>
								<UML:TaggedValue tag="ea_localid" value="6500"/>
								<UML:TaggedValue tag="ea_sourceName" value="PrescribedMedicine"/>
								<UML:TaggedValue tag="ea_targetName" value="PrescribedDose"/>
								<UML:TaggedValue tag="ea_sourceType" value="Class"/>
								<UML:TaggedValue tag="ea_targetType" value="Class"/>
								<UML:TaggedValue tag="ea_sourceID" value="7464"/>
								<UML:TaggedValue tag="ea_targetID" value="7467"/>
								<UML:TaggedValue tag="virtualInheritance" value="0"/>
								<UML:TaggedValue tag="lb" value="1"/>
								<UML:TaggedValue tag="mt" value="hasMedicine"/>
							</UML:ModelElement.taggedValue>
							<UML:Association.connection>
								<UML:AssociationEnd visibility="public" multiplicity="1" aggregation="none" isOrdered="false" targetScope="instance" changeable="none" isNavigable="false" type="EAID_DE6BB62E_6A29_4ab3_91E0_EFD6C851A4C0">
									<UML:ModelElement.taggedValue>
										<UML:TaggedValue tag="containment" value="Unspecified"/>
										<UML:TaggedValue tag="sourcestyle" value="Union=0;Derived=0;AllowDuplicates=0;Owned=0;Navigable=Non-Navigable;"/>
										<UML:TaggedValue tag="ea_end" value="source"/>
									</UML:ModelElement.taggedValue>
								</UML:AssociationEnd>
								<UML:AssociationEnd visibility="public" aggregation="shared" isOrdered="false" targetScope="instance" changeable="none" isNavigable="true" type="EAID_2FF07B53_DA18_4ab5_AAA5_BE8949C44933">
									<UML:ModelElement.taggedValue>
										<UML:TaggedValue tag="containment" value="Unspecified"/>
										<UML:TaggedValue tag="deststyle" value="Union=0;Derived=0;AllowDuplicates=0;Owned=0;Navigable=Navigable;"/>
										<UML:TaggedValue tag="ea_end" value="target"/>
									</UML:ModelElement.taggedValue>
								</UML:AssociationEnd>
							</UML:Association.connection>
						</UML:Association>
						<UML:Association name="hasMedicineDoses" xmi.id="EAID_7D5A7D99_64CF_4654_A409_A14483D0B5C3" visibility="public" isRoot="false" isLeaf="false" isAbstract="false">
							<UML:ModelElement.taggedValue>
								<UML:TaggedValue tag="style" value="3"/>
								<UML:TaggedValue tag="ea_type" value="Aggregation"/>
								<UML:TaggedValue tag="direction" value="Source -&gt; Destination"/>
								<UML:TaggedValue tag="linemode" value="3"/>
								<UML:TaggedValue tag="linecolor" value="-1"/>
								<UML:TaggedValue tag="linewidth" value="0"/>
								<UML:TaggedValue tag="seqno" value="0"/>
								<UML:TaggedValue tag="subtype" value="Weak"/>
								<UML:TaggedValue tag="headStyle" value="0"/>
								<UML:TaggedValue tag="lineStyle" value="0"/>
								<UML:TaggedValue tag="ea_localid" value="6499"/>
								<UML:TaggedValue tag="ea_sourceName" value="PrescribedDose"/>
								<UML:TaggedValue tag="ea_targetName" value="Prescription"/>
								<UML:TaggedValue tag="ea_sourceType" value="Class"/>
								<UML:TaggedValue tag="ea_targetType" value="Class"/>
								<UML:TaggedValue tag="ea_sourceID" value="7467"/>
								<UML:TaggedValue tag="ea_targetID" value="7466"/>
								<UML:TaggedValue tag="virtualInheritance" value="0"/>
								<UML:TaggedValue tag="lb" value="1..*"/>
								<UML:TaggedValue tag="mt" value="hasMedicineDoses"/>
							</UML:ModelElement.taggedValue>
							<UML:Association.connection>
								<UML:AssociationEnd visibility="public" multiplicity="1..*" aggregation="none" isOrdered="false" targetScope="instance" changeable="none" isNavigable="false" type="EAID_2FF07B53_DA18_4ab5_AAA5_BE8949C44933">
									<UML:ModelElement.taggedValue>
										<UML:TaggedValue tag="containment" value="Unspecified"/>
										<UML:TaggedValue tag="sourcestyle" value="Union=0;Derived=0;AllowDuplicates=0;Owned=0;Navigable=Non-Navigable;"/>
										<UML:TaggedValue tag="ea_end" value="source"/>
									</UML:ModelElement.taggedValue>
								</UML:AssociationEnd>
								<UML:AssociationEnd visibility="public" aggregation="shared" isOrdered="false" targetScope="instance" changeable="none" isNavigable="true" type="EAID_A043C0B5_1FD9_4a44_B5E0_4D9DFCBF4549">
									<UML:ModelElement.taggedValue>
										<UML:TaggedValue tag="containment" value="Unspecified"/>
										<UML:TaggedValue tag="deststyle" value="Union=0;Derived=0;AllowDuplicates=0;Owned=0;Navigable=Navigable;"/>
										<UML:TaggedValue tag="ea_end" value="target"/>
									</UML:ModelElement.taggedValue>
								</UML:AssociationEnd>
							</UML:Association.connection>
						</UML:Association>
						<UML:Class name="Dispenser" xmi.id="EAID_39BC8C5E_AD8B_4eed_98A0_36CA98B6A32C" visibility="public" namespace="EAPK_4DB1BF9B_A889_4442_BBDF_E0632A20E77C" isRoot="false" isLeaf="false" isAbstract="false" isActive="false">
							<UML:ModelElement.taggedValue>
								<UML:TaggedValue tag="isSpecification" value="false"/>
								<UML:TaggedValue tag="ea_stype" value="Class"/>
								<UML:TaggedValue tag="ea_ntype" value="0"/>
								<UML:TaggedValue tag="version" value="1.0"/>
								<UML:TaggedValue tag="package" value="EAPK_4DB1BF9B_A889_4442_BBDF_E0632A20E77C"/>
								<UML:TaggedValue tag="date_created" value="2012-02-01 15:30:40"/>
								<UML:TaggedValue tag="date_modified" value="2012-02-01 15:30:52"/>
								<UML:TaggedValue tag="gentype" value="Java"/>
								<UML:TaggedValue tag="tagged" value="0"/>
								<UML:TaggedValue tag="package_name" value="ont.MedMgr"/>
								<UML:TaggedValue tag="phase" value="1.0"/>
								<UML:TaggedValue tag="author" value="Venelin"/>
								<UML:TaggedValue tag="complexity" value="1"/>
								<UML:TaggedValue tag="status" value="Proposed"/>
								<UML:TaggedValue tag="tpos" value="0"/>
								<UML:TaggedValue tag="ea_localid" value="7844"/>
								<UML:TaggedValue tag="ea_eleType" value="element"/>
								<UML:TaggedValue tag="style" value="BackColor=-1;BorderColor=-1;BorderWidth=-1;FontColor=-1;VSwimLanes=1;HSwimLanes=1;BorderStyle=0;"/>
							</UML:ModelElement.taggedValue>
						</UML:Class>
						<UML:Association name="useDispenser" xmi.id="EAID_620033AD_8011_48ca_A8C2_6660E5FAA47A" visibility="public" isRoot="false" isLeaf="false" isAbstract="false">
							<UML:ModelElement.taggedValue>
								<UML:TaggedValue tag="style" value="3"/>
								<UML:TaggedValue tag="ea_type" value="Aggregation"/>
								<UML:TaggedValue tag="direction" value="Source -&gt; Destination"/>
								<UML:TaggedValue tag="linemode" value="3"/>
								<UML:TaggedValue tag="linecolor" value="-1"/>
								<UML:TaggedValue tag="linewidth" value="0"/>
								<UML:TaggedValue tag="seqno" value="0"/>
								<UML:TaggedValue tag="subtype" value="Weak"/>
								<UML:TaggedValue tag="headStyle" value="0"/>
								<UML:TaggedValue tag="lineStyle" value="0"/>
								<UML:TaggedValue tag="ea_localid" value="6857"/>
								<UML:TaggedValue tag="ea_sourceName" value="Dispenser"/>
								<UML:TaggedValue tag="ea_targetName" value="Intake"/>
								<UML:TaggedValue tag="ea_sourceType" value="Class"/>
								<UML:TaggedValue tag="ea_targetType" value="Class"/>
								<UML:TaggedValue tag="ea_sourceID" value="7844"/>
								<UML:TaggedValue tag="ea_targetID" value="7465"/>
								<UML:TaggedValue tag="virtualInheritance" value="0"/>
								<UML:TaggedValue tag="mt" value="useDispenser"/>
							</UML:ModelElement.taggedValue>
							<UML:Association.connection>
								<UML:AssociationEnd visibility="public" aggregation="none" isOrdered="false" targetScope="instance" changeable="none" isNavigable="false" type="EAID_39BC8C5E_AD8B_4eed_98A0_36CA98B6A32C">
									<UML:ModelElement.taggedValue>
										<UML:TaggedValue tag="containment" value="Unspecified"/>
										<UML:TaggedValue tag="sourcestyle" value="Union=0;Derived=0;AllowDuplicates=0;Owned=0;Navigable=Non-Navigable;"/>
										<UML:TaggedValue tag="ea_end" value="source"/>
									</UML:ModelElement.taggedValue>
								</UML:AssociationEnd>
								<UML:AssociationEnd visibility="public" aggregation="shared" isOrdered="false" targetScope="instance" changeable="none" isNavigable="true" type="EAID_D6D1CDC5_3805_4209_BFDB_E29147C7C283">
									<UML:ModelElement.taggedValue>
										<UML:TaggedValue tag="containment" value="Unspecified"/>
										<UML:TaggedValue tag="deststyle" value="Union=0;Derived=0;AllowDuplicates=0;Owned=0;Navigable=Navigable;"/>
										<UML:TaggedValue tag="ea_end" value="target"/>
									</UML:ModelElement.taggedValue>
								</UML:AssociationEnd>
							</UML:Association.connection>
						</UML:Association>
						<UML:Class name="Medication" xmi.id="EAID_4615C46B_94AF_4169_AD12_B43BE6EB1B5F" visibility="public" namespace="EAPK_4DB1BF9B_A889_4442_BBDF_E0632A20E77C" isRoot="false" isLeaf="false" isAbstract="false" isActive="false">
							<UML:ModelElement.taggedValue>
								<UML:TaggedValue tag="isSpecification" value="false"/>
								<UML:TaggedValue tag="ea_stype" value="Class"/>
								<UML:TaggedValue tag="ea_ntype" value="0"/>
								<UML:TaggedValue tag="version" value="1.0"/>
								<UML:TaggedValue tag="package" value="EAPK_4DB1BF9B_A889_4442_BBDF_E0632A20E77C"/>
								<UML:TaggedValue tag="date_created" value="2012-01-27 14:56:22"/>
								<UML:TaggedValue tag="date_modified" value="2012-01-27 14:56:43"/>
								<UML:TaggedValue tag="gentype" value="Java"/>
								<UML:TaggedValue tag="tagged" value="0"/>
								<UML:TaggedValue tag="package_name" value="ont.MedMgr"/>
								<UML:TaggedValue tag="phase" value="1.0"/>
								<UML:TaggedValue tag="author" value="Venelin"/>
								<UML:TaggedValue tag="complexity" value="1"/>
								<UML:TaggedValue tag="status" value="Proposed"/>
								<UML:TaggedValue tag="tpos" value="0"/>
								<UML:TaggedValue tag="ea_localid" value="7463"/>
								<UML:TaggedValue tag="ea_eleType" value="element"/>
								<UML:TaggedValue tag="style" value="BackColor=-1;BorderColor=-1;BorderWidth=-1;FontColor=-1;VSwimLanes=1;HSwimLanes=1;BorderStyle=0;"/>
							</UML:ModelElement.taggedValue>
						</UML:Class>
						<UML:Class name="Precaution" xmi.id="EAID_7609610B_51A5_4b72_B7DD_DF4E35D63C6B" visibility="public" namespace="EAPK_4DB1BF9B_A889_4442_BBDF_E0632A20E77C" isRoot="false" isLeaf="false" isAbstract="false" isActive="false">
							<UML:ModelElement.taggedValue>
								<UML:TaggedValue tag="documentation" value="Current precautions for the specific user as derived from the Incompliances and SideEffects attributes of all prescribed medicines"/>
								<UML:TaggedValue tag="isSpecification" value="false"/>
								<UML:TaggedValue tag="ea_stype" value="Class"/>
								<UML:TaggedValue tag="ea_ntype" value="0"/>
								<UML:TaggedValue tag="version" value="1.0"/>
								<UML:TaggedValue tag="package" value="EAPK_4DB1BF9B_A889_4442_BBDF_E0632A20E77C"/>
								<UML:TaggedValue tag="date_created" value="2012-01-27 15:35:17"/>
								<UML:TaggedValue tag="date_modified" value="2012-02-01 15:26:44"/>
								<UML:TaggedValue tag="gentype" value="Java"/>
								<UML:TaggedValue tag="tagged" value="0"/>
								<UML:TaggedValue tag="package_name" value="ont.MedMgr"/>
								<UML:TaggedValue tag="phase" value="1.0"/>
								<UML:TaggedValue tag="author" value="Venelin"/>
								<UML:TaggedValue tag="complexity" value="1"/>
								<UML:TaggedValue tag="status" value="Proposed"/>
								<UML:TaggedValue tag="tpos" value="0"/>
								<UML:TaggedValue tag="ea_localid" value="7468"/>
								<UML:TaggedValue tag="ea_eleType" value="element"/>
								<UML:TaggedValue tag="style" value="BackColor=-1;BorderColor=-1;BorderWidth=-1;FontColor=-1;VSwimLanes=1;HSwimLanes=1;BorderStyle=0;"/>
							</UML:ModelElement.taggedValue>
							<UML:Classifier.feature>
								<UML:Attribute name="Incompliances[]" changeable="none" visibility="private" ownerScope="instance" targetScope="instance">
									<UML:Attribute.initialValue>
										<UML:Expression/>
									</UML:Attribute.initialValue>
									<UML:StructuralFeature.type>
										<UML:Classifier xmi.idref="eaxmiid1"/>
									</UML:StructuralFeature.type>
									<UML:ModelElement.taggedValue>
										<UML:TaggedValue tag="description" value="List of incompliances"/>
										<UML:TaggedValue tag="type" value="char"/>
										<UML:TaggedValue tag="derived" value="0"/>
										<UML:TaggedValue tag="containment" value="Not Specified"/>
										<UML:TaggedValue tag="ordered" value="0"/>
										<UML:TaggedValue tag="collection" value="false"/>
										<UML:TaggedValue tag="position" value="0"/>
										<UML:TaggedValue tag="lowerBound" value="1"/>
										<UML:TaggedValue tag="upperBound" value="1"/>
										<UML:TaggedValue tag="duplicates" value="0"/>
										<UML:TaggedValue tag="ea_guid" value="{6A870C15-EC1D-40fc-A284-D01E27271CF1}"/>
										<UML:TaggedValue tag="ea_localid" value="1920"/>
										<UML:TaggedValue tag="styleex" value="IsLiteral=0;volatile=0;"/>
									</UML:ModelElement.taggedValue>
								</UML:Attribute>
								<UML:Attribute name="SideEffects[]" changeable="none" visibility="private" ownerScope="instance" targetScope="instance">
									<UML:Attribute.initialValue>
										<UML:Expression/>
									</UML:Attribute.initialValue>
									<UML:StructuralFeature.type>
										<UML:Classifier xmi.idref="eaxmiid1"/>
									</UML:StructuralFeature.type>
									<UML:ModelElement.taggedValue>
										<UML:TaggedValue tag="description" value="List of side effects"/>
										<UML:TaggedValue tag="type" value="char"/>
										<UML:TaggedValue tag="derived" value="0"/>
										<UML:TaggedValue tag="containment" value="Not Specified"/>
										<UML:TaggedValue tag="ordered" value="0"/>
										<UML:TaggedValue tag="collection" value="false"/>
										<UML:TaggedValue tag="position" value="1"/>
										<UML:TaggedValue tag="lowerBound" value="1"/>
										<UML:TaggedValue tag="upperBound" value="1"/>
										<UML:TaggedValue tag="duplicates" value="0"/>
										<UML:TaggedValue tag="ea_guid" value="{177A891A-3FF3-475e-97B2-5DCC9C3630B1}"/>
										<UML:TaggedValue tag="ea_localid" value="1921"/>
										<UML:TaggedValue tag="styleex" value="IsLiteral=0;volatile=0;"/>
									</UML:ModelElement.taggedValue>
								</UML:Attribute>
							</UML:Classifier.feature>
						</UML:Class>
						<UML:Class name="Prescription" xmi.id="EAID_A043C0B5_1FD9_4a44_B5E0_4D9DFCBF4549" visibility="public" namespace="EAPK_4DB1BF9B_A889_4442_BBDF_E0632A20E77C" isRoot="false" isLeaf="false" isAbstract="false" isActive="false">
							<UML:ModelElement.taggedValue>
								<UML:TaggedValue tag="isSpecification" value="false"/>
								<UML:TaggedValue tag="ea_stype" value="Class"/>
								<UML:TaggedValue tag="ea_ntype" value="0"/>
								<UML:TaggedValue tag="version" value="1.0"/>
								<UML:TaggedValue tag="package" value="EAPK_4DB1BF9B_A889_4442_BBDF_E0632A20E77C"/>
								<UML:TaggedValue tag="date_created" value="2012-01-27 15:10:39"/>
								<UML:TaggedValue tag="date_modified" value="2012-01-27 15:10:52"/>
								<UML:TaggedValue tag="gentype" value="Java"/>
								<UML:TaggedValue tag="tagged" value="0"/>
								<UML:TaggedValue tag="package_name" value="ont.MedMgr"/>
								<UML:TaggedValue tag="phase" value="1.0"/>
								<UML:TaggedValue tag="author" value="Venelin"/>
								<UML:TaggedValue tag="complexity" value="1"/>
								<UML:TaggedValue tag="status" value="Proposed"/>
								<UML:TaggedValue tag="tpos" value="0"/>
								<UML:TaggedValue tag="ea_localid" value="7466"/>
								<UML:TaggedValue tag="ea_eleType" value="element"/>
								<UML:TaggedValue tag="style" value="BackColor=-1;BorderColor=-1;BorderWidth=-1;FontColor=-1;VSwimLanes=1;HSwimLanes=1;BorderStyle=0;"/>
							</UML:ModelElement.taggedValue>
							<UML:Classifier.feature>
								<UML:Attribute name="IssueDate" changeable="none" visibility="private" ownerScope="instance" targetScope="instance">
									<UML:Attribute.initialValue>
										<UML:Expression/>
									</UML:Attribute.initialValue>
									<UML:StructuralFeature.type>
										<UML:Classifier xmi.idref="eaxmiid2"/>
									</UML:StructuralFeature.type>
									<UML:ModelElement.taggedValue>
										<UML:TaggedValue tag="type" value="long"/>
										<UML:TaggedValue tag="derived" value="0"/>
										<UML:TaggedValue tag="containment" value="Not Specified"/>
										<UML:TaggedValue tag="ordered" value="0"/>
										<UML:TaggedValue tag="collection" value="false"/>
										<UML:TaggedValue tag="position" value="0"/>
										<UML:TaggedValue tag="lowerBound" value="1"/>
										<UML:TaggedValue tag="upperBound" value="1"/>
										<UML:TaggedValue tag="duplicates" value="0"/>
										<UML:TaggedValue tag="ea_guid" value="{4A679141-B84B-4ad3-9E3E-D92D56F4408B}"/>
										<UML:TaggedValue tag="ea_localid" value="1910"/>
										<UML:TaggedValue tag="styleex" value="IsLiteral=0;volatile=0;"/>
									</UML:ModelElement.taggedValue>
								</UML:Attribute>
								<UML:Attribute name="IssuedBy" changeable="none" visibility="private" ownerScope="instance" targetScope="instance">
									<UML:Attribute.initialValue>
										<UML:Expression/>
									</UML:Attribute.initialValue>
									<UML:StructuralFeature.type>
										<UML:Classifier xmi.idref="EAID_0695D040_8E2F_4b8a_97B8_8D5409F6D124"/>
									</UML:StructuralFeature.type>
									<UML:ModelElement.taggedValue>
										<UML:TaggedValue tag="type" value="Medical doctor"/>
										<UML:TaggedValue tag="derived" value="0"/>
										<UML:TaggedValue tag="containment" value="Not Specified"/>
										<UML:TaggedValue tag="ordered" value="0"/>
										<UML:TaggedValue tag="collection" value="false"/>
										<UML:TaggedValue tag="position" value="1"/>
										<UML:TaggedValue tag="lowerBound" value="1"/>
										<UML:TaggedValue tag="upperBound" value="1"/>
										<UML:TaggedValue tag="duplicates" value="0"/>
										<UML:TaggedValue tag="ea_guid" value="{DC1D11A5-ABBF-4d16-8EE7-9B0A7780C427}"/>
										<UML:TaggedValue tag="ea_localid" value="1911"/>
										<UML:TaggedValue tag="styleex" value="IsLiteral=0;volatile=0;"/>
									</UML:ModelElement.taggedValue>
								</UML:Attribute>
								<UML:Attribute name="TerminatedBy" changeable="none" visibility="private" ownerScope="instance" targetScope="instance">
									<UML:Attribute.initialValue>
										<UML:Expression/>
									</UML:Attribute.initialValue>
									<UML:StructuralFeature.type>
										<UML:Classifier xmi.idref="EAID_0695D040_8E2F_4b8a_97B8_8D5409F6D124"/>
									</UML:StructuralFeature.type>
									<UML:ModelElement.taggedValue>
										<UML:TaggedValue tag="description" value="reference to the doctor, who suspended the prescription"/>
										<UML:TaggedValue tag="type" value="Medical doctor"/>
										<UML:TaggedValue tag="derived" value="0"/>
										<UML:TaggedValue tag="containment" value="Not Specified"/>
										<UML:TaggedValue tag="ordered" value="0"/>
										<UML:TaggedValue tag="collection" value="false"/>
										<UML:TaggedValue tag="position" value="3"/>
										<UML:TaggedValue tag="lowerBound" value="1"/>
										<UML:TaggedValue tag="upperBound" value="1"/>
										<UML:TaggedValue tag="duplicates" value="0"/>
										<UML:TaggedValue tag="ea_guid" value="{7160A6E2-6D06-4efc-A97E-F1BEEA8846B8}"/>
										<UML:TaggedValue tag="ea_localid" value="1914"/>
										<UML:TaggedValue tag="styleex" value="IsLiteral=0;volatile=0;"/>
									</UML:ModelElement.taggedValue>
								</UML:Attribute>
								<UML:Attribute name="TerminatedOn" changeable="none" visibility="private" ownerScope="instance" targetScope="instance">
									<UML:Attribute.initialValue>
										<UML:Expression/>
									</UML:Attribute.initialValue>
									<UML:StructuralFeature.type>
										<UML:Classifier xmi.idref="eaxmiid2"/>
									</UML:StructuralFeature.type>
									<UML:ModelElement.taggedValue>
										<UML:TaggedValue tag="description" value="Date on which the prescription is made invalid (due to various reasons of the doctor)"/>
										<UML:TaggedValue tag="type" value="long"/>
										<UML:TaggedValue tag="derived" value="0"/>
										<UML:TaggedValue tag="containment" value="Not Specified"/>
										<UML:TaggedValue tag="ordered" value="0"/>
										<UML:TaggedValue tag="collection" value="false"/>
										<UML:TaggedValue tag="position" value="4"/>
										<UML:TaggedValue tag="lowerBound" value="1"/>
										<UML:TaggedValue tag="upperBound" value="1"/>
										<UML:TaggedValue tag="duplicates" value="0"/>
										<UML:TaggedValue tag="ea_guid" value="{DB14D3D9-2676-4179-BD16-80DD9BE1B8C5}"/>
										<UML:TaggedValue tag="ea_localid" value="1913"/>
										<UML:TaggedValue tag="styleex" value="IsLiteral=0;volatile=0;"/>
									</UML:ModelElement.taggedValue>
								</UML:Attribute>
								<UML:Attribute name="Valid" changeable="none" visibility="private" ownerScope="instance" targetScope="instance">
									<UML:Attribute.initialValue>
										<UML:Expression/>
									</UML:Attribute.initialValue>
									<UML:StructuralFeature.type>
										<UML:Classifier xmi.idref="eaxmiid3"/>
									</UML:StructuralFeature.type>
									<UML:ModelElement.taggedValue>
										<UML:TaggedValue tag="description" value="Status of the prescription"/>
										<UML:TaggedValue tag="type" value="boolean"/>
										<UML:TaggedValue tag="derived" value="0"/>
										<UML:TaggedValue tag="containment" value="Not Specified"/>
										<UML:TaggedValue tag="ordered" value="0"/>
										<UML:TaggedValue tag="collection" value="false"/>
										<UML:TaggedValue tag="position" value="5"/>
										<UML:TaggedValue tag="lowerBound" value="1"/>
										<UML:TaggedValue tag="upperBound" value="1"/>
										<UML:TaggedValue tag="duplicates" value="0"/>
										<UML:TaggedValue tag="ea_guid" value="{67BF6046-7B98-4a82-82EF-2A24164783C1}"/>
										<UML:TaggedValue tag="ea_localid" value="1912"/>
										<UML:TaggedValue tag="styleex" value="IsLiteral=0;volatile=0;"/>
									</UML:ModelElement.taggedValue>
								</UML:Attribute>
							</UML:Classifier.feature>
						</UML:Class>
						<UML:Class name="IntakeMedicine" xmi.id="EAID_CB5BDDFF_8D6E_44c1_9D57_CE51478C1DA9" visibility="public" namespace="EAPK_4DB1BF9B_A889_4442_BBDF_E0632A20E77C" isRoot="false" isLeaf="false" isAbstract="false" isActive="false">
							<UML:ModelElement.taggedValue>
								<UML:TaggedValue tag="isSpecification" value="false"/>
								<UML:TaggedValue tag="ea_stype" value="Class"/>
								<UML:TaggedValue tag="ea_ntype" value="0"/>
								<UML:TaggedValue tag="version" value="1.0"/>
								<UML:TaggedValue tag="package" value="EAPK_4DB1BF9B_A889_4442_BBDF_E0632A20E77C"/>
								<UML:TaggedValue tag="date_created" value="2012-01-27 15:51:14"/>
								<UML:TaggedValue tag="date_modified" value="2012-01-27 15:51:28"/>
								<UML:TaggedValue tag="gentype" value="Java"/>
								<UML:TaggedValue tag="tagged" value="0"/>
								<UML:TaggedValue tag="package_name" value="ont.MedMgr"/>
								<UML:TaggedValue tag="phase" value="1.0"/>
								<UML:TaggedValue tag="author" value="Venelin"/>
								<UML:TaggedValue tag="complexity" value="1"/>
								<UML:TaggedValue tag="status" value="Proposed"/>
								<UML:TaggedValue tag="tpos" value="0"/>
								<UML:TaggedValue tag="ea_localid" value="7470"/>
								<UML:TaggedValue tag="ea_eleType" value="element"/>
								<UML:TaggedValue tag="style" value="BackColor=-1;BorderColor=-1;BorderWidth=-1;FontColor=-1;VSwimLanes=1;HSwimLanes=1;BorderStyle=0;"/>
							</UML:ModelElement.taggedValue>
							<UML:Classifier.feature>
								<UML:Attribute name="ID" changeable="none" visibility="private" ownerScope="instance" targetScope="instance">
									<UML:Attribute.initialValue>
										<UML:Expression/>
									</UML:Attribute.initialValue>
									<UML:StructuralFeature.type>
										<UML:Classifier xmi.idref="eaxmiid1"/>
									</UML:StructuralFeature.type>
									<UML:ModelElement.taggedValue>
										<UML:TaggedValue tag="description" value="international identifier of the product"/>
										<UML:TaggedValue tag="type" value="char"/>
										<UML:TaggedValue tag="derived" value="0"/>
										<UML:TaggedValue tag="containment" value="Not Specified"/>
										<UML:TaggedValue tag="ordered" value="0"/>
										<UML:TaggedValue tag="collection" value="false"/>
										<UML:TaggedValue tag="position" value="0"/>
										<UML:TaggedValue tag="lowerBound" value="1"/>
										<UML:TaggedValue tag="upperBound" value="1"/>
										<UML:TaggedValue tag="duplicates" value="0"/>
										<UML:TaggedValue tag="ea_guid" value="{FB824680-EB16-46d1-A914-5812C6BAF430}"/>
										<UML:TaggedValue tag="ea_localid" value="1928"/>
										<UML:TaggedValue tag="styleex" value="IsLiteral=0;volatile=0;"/>
									</UML:ModelElement.taggedValue>
								</UML:Attribute>
								<UML:Attribute name="Incompliances[]" changeable="none" visibility="private" ownerScope="instance" targetScope="instance">
									<UML:Attribute.initialValue>
										<UML:Expression/>
									</UML:Attribute.initialValue>
									<UML:StructuralFeature.type>
										<UML:Classifier xmi.idref="eaxmiid1"/>
									</UML:StructuralFeature.type>
									<UML:ModelElement.taggedValue>
										<UML:TaggedValue tag="description" value="List of incompliances for this medicine"/>
										<UML:TaggedValue tag="type" value="char"/>
										<UML:TaggedValue tag="derived" value="0"/>
										<UML:TaggedValue tag="containment" value="Not Specified"/>
										<UML:TaggedValue tag="ordered" value="0"/>
										<UML:TaggedValue tag="collection" value="false"/>
										<UML:TaggedValue tag="position" value="1"/>
										<UML:TaggedValue tag="lowerBound" value="1"/>
										<UML:TaggedValue tag="upperBound" value="1"/>
										<UML:TaggedValue tag="duplicates" value="0"/>
										<UML:TaggedValue tag="ea_guid" value="{90012AFE-667A-4548-89B7-3A7931B58516}"/>
										<UML:TaggedValue tag="ea_localid" value="1930"/>
										<UML:TaggedValue tag="styleex" value="IsLiteral=0;volatile=0;"/>
									</UML:ModelElement.taggedValue>
								</UML:Attribute>
								<UML:Attribute name="Name" changeable="none" visibility="private" ownerScope="instance" targetScope="instance">
									<UML:Attribute.initialValue>
										<UML:Expression/>
									</UML:Attribute.initialValue>
									<UML:StructuralFeature.type>
										<UML:Classifier xmi.idref="eaxmiid1"/>
									</UML:StructuralFeature.type>
									<UML:ModelElement.taggedValue>
										<UML:TaggedValue tag="type" value="char"/>
										<UML:TaggedValue tag="derived" value="0"/>
										<UML:TaggedValue tag="containment" value="Not Specified"/>
										<UML:TaggedValue tag="ordered" value="0"/>
										<UML:TaggedValue tag="collection" value="false"/>
										<UML:TaggedValue tag="position" value="2"/>
										<UML:TaggedValue tag="lowerBound" value="1"/>
										<UML:TaggedValue tag="upperBound" value="1"/>
										<UML:TaggedValue tag="duplicates" value="0"/>
										<UML:TaggedValue tag="ea_guid" value="{D874C0FE-499D-4db2-8E85-6FCF23ECE287}"/>
										<UML:TaggedValue tag="ea_localid" value="1933"/>
										<UML:TaggedValue tag="styleex" value="IsLiteral=0;volatile=0;"/>
									</UML:ModelElement.taggedValue>
								</UML:Attribute>
								<UML:Attribute name="PrescribedMedicine" changeable="none" visibility="private" ownerScope="instance" targetScope="instance">
									<UML:Attribute.initialValue>
										<UML:Expression/>
									</UML:Attribute.initialValue>
									<UML:StructuralFeature.type>
										<UML:Classifier xmi.idref="EAID_DE6BB62E_6A29_4ab3_91E0_EFD6C851A4C0"/>
									</UML:StructuralFeature.type>
									<UML:ModelElement.taggedValue>
										<UML:TaggedValue tag="description" value="a reference to the prescribed medicine in case the pharmacist has provided an alternative brand "/>
										<UML:TaggedValue tag="type" value="PrescribedMedicine"/>
										<UML:TaggedValue tag="derived" value="0"/>
										<UML:TaggedValue tag="containment" value="Not Specified"/>
										<UML:TaggedValue tag="ordered" value="0"/>
										<UML:TaggedValue tag="collection" value="false"/>
										<UML:TaggedValue tag="position" value="3"/>
										<UML:TaggedValue tag="lowerBound" value="1"/>
										<UML:TaggedValue tag="upperBound" value="1"/>
										<UML:TaggedValue tag="duplicates" value="0"/>
										<UML:TaggedValue tag="ea_guid" value="{7171FFF6-DD4E-4f0e-94E7-04C991C2292A}"/>
										<UML:TaggedValue tag="ea_localid" value="1929"/>
										<UML:TaggedValue tag="styleex" value="IsLiteral=0;volatile=0;"/>
									</UML:ModelElement.taggedValue>
								</UML:Attribute>
								<UML:Attribute name="SideEffects[]" changeable="none" visibility="private" ownerScope="instance" targetScope="instance">
									<UML:Attribute.initialValue>
										<UML:Expression/>
									</UML:Attribute.initialValue>
									<UML:StructuralFeature.type>
										<UML:Classifier xmi.idref="eaxmiid1"/>
									</UML:StructuralFeature.type>
									<UML:ModelElement.taggedValue>
										<UML:TaggedValue tag="description" value="List of side effects"/>
										<UML:TaggedValue tag="type" value="char"/>
										<UML:TaggedValue tag="derived" value="0"/>
										<UML:TaggedValue tag="containment" value="Not Specified"/>
										<UML:TaggedValue tag="ordered" value="0"/>
										<UML:TaggedValue tag="collection" value="false"/>
										<UML:TaggedValue tag="position" value="4"/>
										<UML:TaggedValue tag="lowerBound" value="1"/>
										<UML:TaggedValue tag="upperBound" value="1"/>
										<UML:TaggedValue tag="duplicates" value="0"/>
										<UML:TaggedValue tag="ea_guid" value="{A982BB52-727E-49a2-B648-A8AB0B74FCF1}"/>
										<UML:TaggedValue tag="ea_localid" value="1931"/>
										<UML:TaggedValue tag="styleex" value="IsLiteral=0;volatile=0;"/>
									</UML:ModelElement.taggedValue>
								</UML:Attribute>
							</UML:Classifier.feature>
						</UML:Class>
						<UML:Class name="Intake" xmi.id="EAID_D6D1CDC5_3805_4209_BFDB_E29147C7C283" visibility="public" namespace="EAPK_4DB1BF9B_A889_4442_BBDF_E0632A20E77C" isRoot="false" isLeaf="false" isAbstract="false" isActive="false">
							<UML:ModelElement.taggedValue>
								<UML:TaggedValue tag="isSpecification" value="false"/>
								<UML:TaggedValue tag="ea_stype" value="Class"/>
								<UML:TaggedValue tag="ea_ntype" value="0"/>
								<UML:TaggedValue tag="version" value="1.0"/>
								<UML:TaggedValue tag="package" value="EAPK_4DB1BF9B_A889_4442_BBDF_E0632A20E77C"/>
								<UML:TaggedValue tag="date_created" value="2012-01-27 15:03:23"/>
								<UML:TaggedValue tag="date_modified" value="2012-01-27 15:03:31"/>
								<UML:TaggedValue tag="gentype" value="Java"/>
								<UML:TaggedValue tag="tagged" value="0"/>
								<UML:TaggedValue tag="package_name" value="ont.MedMgr"/>
								<UML:TaggedValue tag="phase" value="1.0"/>
								<UML:TaggedValue tag="author" value="Venelin"/>
								<UML:TaggedValue tag="complexity" value="1"/>
								<UML:TaggedValue tag="status" value="Proposed"/>
								<UML:TaggedValue tag="tpos" value="0"/>
								<UML:TaggedValue tag="ea_localid" value="7465"/>
								<UML:TaggedValue tag="ea_eleType" value="element"/>
								<UML:TaggedValue tag="style" value="BackColor=-1;BorderColor=-1;BorderWidth=-1;FontColor=-1;VSwimLanes=1;HSwimLanes=1;BorderStyle=0;"/>
							</UML:ModelElement.taggedValue>
							<UML:Classifier.feature>
								<UML:Attribute name="Dispenser" changeable="none" visibility="private" ownerScope="instance" targetScope="instance">
									<UML:Attribute.initialValue>
										<UML:Expression/>
									</UML:Attribute.initialValue>
									<UML:StructuralFeature.type>
										<UML:Classifier xmi.idref="EAID_1985356A_6E50_4781_9DF9_EA92F3AA0BCD"/>
									</UML:StructuralFeature.type>
									<UML:ModelElement.taggedValue>
										<UML:TaggedValue tag="type" value="Pill dispenser"/>
										<UML:TaggedValue tag="derived" value="0"/>
										<UML:TaggedValue tag="containment" value="Not Specified"/>
										<UML:TaggedValue tag="ordered" value="0"/>
										<UML:TaggedValue tag="collection" value="false"/>
										<UML:TaggedValue tag="position" value="0"/>
										<UML:TaggedValue tag="lowerBound" value="1"/>
										<UML:TaggedValue tag="upperBound" value="1"/>
										<UML:TaggedValue tag="duplicates" value="0"/>
										<UML:TaggedValue tag="ea_guid" value="{1DBC2DE6-77FC-40d3-A81D-9547E4522032}"/>
										<UML:TaggedValue tag="ea_localid" value="2025"/>
										<UML:TaggedValue tag="styleex" value="IsLiteral=0;volatile=0;"/>
									</UML:ModelElement.taggedValue>
								</UML:Attribute>
								<UML:Attribute name="IntakeTime" changeable="none" visibility="private" ownerScope="instance" targetScope="instance">
									<UML:Attribute.initialValue>
										<UML:Expression/>
									</UML:Attribute.initialValue>
									<UML:StructuralFeature.type>
										<UML:Classifier xmi.idref="eaxmiid2"/>
									</UML:StructuralFeature.type>
									<UML:ModelElement.taggedValue>
										<UML:TaggedValue tag="description" value="Actual intake time (null= not taken)"/>
										<UML:TaggedValue tag="type" value="long"/>
										<UML:TaggedValue tag="derived" value="0"/>
										<UML:TaggedValue tag="containment" value="Not Specified"/>
										<UML:TaggedValue tag="ordered" value="0"/>
										<UML:TaggedValue tag="collection" value="false"/>
										<UML:TaggedValue tag="position" value="1"/>
										<UML:TaggedValue tag="lowerBound" value="1"/>
										<UML:TaggedValue tag="upperBound" value="1"/>
										<UML:TaggedValue tag="duplicates" value="0"/>
										<UML:TaggedValue tag="ea_guid" value="{3DF45A40-362E-46bb-9903-1AE3D5DF9A92}"/>
										<UML:TaggedValue tag="ea_localid" value="1906"/>
										<UML:TaggedValue tag="styleex" value="IsLiteral=0;volatile=0;"/>
									</UML:ModelElement.taggedValue>
								</UML:Attribute>
								<UML:Attribute name="PlannedTime" changeable="none" visibility="private" ownerScope="instance" targetScope="instance">
									<UML:Attribute.initialValue>
										<UML:Expression/>
									</UML:Attribute.initialValue>
									<UML:StructuralFeature.type>
										<UML:Classifier xmi.idref="eaxmiid2"/>
									</UML:StructuralFeature.type>
									<UML:ModelElement.taggedValue>
										<UML:TaggedValue tag="description" value="Planned intake time"/>
										<UML:TaggedValue tag="type" value="long"/>
										<UML:TaggedValue tag="derived" value="0"/>
										<UML:TaggedValue tag="containment" value="Not Specified"/>
										<UML:TaggedValue tag="ordered" value="0"/>
										<UML:TaggedValue tag="collection" value="false"/>
										<UML:TaggedValue tag="position" value="2"/>
										<UML:TaggedValue tag="lowerBound" value="1"/>
										<UML:TaggedValue tag="upperBound" value="1"/>
										<UML:TaggedValue tag="duplicates" value="0"/>
										<UML:TaggedValue tag="ea_guid" value="{8D97A2EF-949C-47f3-A87D-400187EF34A1}"/>
										<UML:TaggedValue tag="ea_localid" value="1904"/>
										<UML:TaggedValue tag="styleex" value="IsLiteral=0;volatile=0;"/>
									</UML:ModelElement.taggedValue>
								</UML:Attribute>
							</UML:Classifier.feature>
						</UML:Class>
						<UML:Class name="PrescribedMedicine" xmi.id="EAID_DE6BB62E_6A29_4ab3_91E0_EFD6C851A4C0" visibility="public" namespace="EAPK_4DB1BF9B_A889_4442_BBDF_E0632A20E77C" isRoot="false" isLeaf="false" isAbstract="false" isActive="false">
							<UML:ModelElement.taggedValue>
								<UML:TaggedValue tag="isSpecification" value="false"/>
								<UML:TaggedValue tag="ea_stype" value="Class"/>
								<UML:TaggedValue tag="ea_ntype" value="0"/>
								<UML:TaggedValue tag="version" value="1.0"/>
								<UML:TaggedValue tag="package" value="EAPK_4DB1BF9B_A889_4442_BBDF_E0632A20E77C"/>
								<UML:TaggedValue tag="date_created" value="2012-01-27 14:57:15"/>
								<UML:TaggedValue tag="date_modified" value="2012-01-27 16:03:24"/>
								<UML:TaggedValue tag="gentype" value="Java"/>
								<UML:TaggedValue tag="tagged" value="0"/>
								<UML:TaggedValue tag="package_name" value="ont.MedMgr"/>
								<UML:TaggedValue tag="phase" value="1.0"/>
								<UML:TaggedValue tag="author" value="Venelin"/>
								<UML:TaggedValue tag="complexity" value="1"/>
								<UML:TaggedValue tag="status" value="Proposed"/>
								<UML:TaggedValue tag="tpos" value="0"/>
								<UML:TaggedValue tag="ea_localid" value="7464"/>
								<UML:TaggedValue tag="ea_eleType" value="element"/>
								<UML:TaggedValue tag="$ea_attsclassified" value="{7171FFF6-DD4E-4f0e-94E7-04C991C2292A}"/>
								<UML:TaggedValue tag="style" value="BackColor=-1;BorderColor=-1;BorderWidth=-1;FontColor=-1;VSwimLanes=1;HSwimLanes=1;BorderStyle=0;"/>
							</UML:ModelElement.taggedValue>
							<UML:Classifier.feature>
								<UML:Attribute name="ID" changeable="none" visibility="private" ownerScope="instance" targetScope="instance">
									<UML:Attribute.initialValue>
										<UML:Expression/>
									</UML:Attribute.initialValue>
									<UML:StructuralFeature.type>
										<UML:Classifier xmi.idref="eaxmiid1"/>
									</UML:StructuralFeature.type>
									<UML:ModelElement.taggedValue>
										<UML:TaggedValue tag="type" value="char"/>
										<UML:TaggedValue tag="derived" value="0"/>
										<UML:TaggedValue tag="containment" value="Not Specified"/>
										<UML:TaggedValue tag="ordered" value="0"/>
										<UML:TaggedValue tag="collection" value="false"/>
										<UML:TaggedValue tag="position" value="0"/>
										<UML:TaggedValue tag="lowerBound" value="1"/>
										<UML:TaggedValue tag="upperBound" value="1"/>
										<UML:TaggedValue tag="duplicates" value="0"/>
										<UML:TaggedValue tag="ea_guid" value="{74E371C9-EA5D-4565-9523-78EA492A5E8F}"/>
										<UML:TaggedValue tag="ea_localid" value="1900"/>
										<UML:TaggedValue tag="styleex" value="IsLiteral=0;volatile=0;"/>
									</UML:ModelElement.taggedValue>
								</UML:Attribute>
								<UML:Attribute name="Name" changeable="none" visibility="private" ownerScope="instance" targetScope="instance">
									<UML:Attribute.initialValue>
										<UML:Expression/>
									</UML:Attribute.initialValue>
									<UML:StructuralFeature.type>
										<UML:Classifier xmi.idref="eaxmiid1"/>
									</UML:StructuralFeature.type>
									<UML:ModelElement.taggedValue>
										<UML:TaggedValue tag="type" value="char"/>
										<UML:TaggedValue tag="derived" value="0"/>
										<UML:TaggedValue tag="containment" value="Not Specified"/>
										<UML:TaggedValue tag="ordered" value="0"/>
										<UML:TaggedValue tag="collection" value="false"/>
										<UML:TaggedValue tag="position" value="1"/>
										<UML:TaggedValue tag="lowerBound" value="1"/>
										<UML:TaggedValue tag="upperBound" value="1"/>
										<UML:TaggedValue tag="duplicates" value="0"/>
										<UML:TaggedValue tag="ea_guid" value="{D2920C09-DEA5-4771-8C21-8114E60FD8BE}"/>
										<UML:TaggedValue tag="ea_localid" value="1901"/>
										<UML:TaggedValue tag="styleex" value="IsLiteral=0;volatile=0;"/>
									</UML:ModelElement.taggedValue>
								</UML:Attribute>
							</UML:Classifier.feature>
						</UML:Class>
					</UML:Namespace.ownedElement>
				</UML:Package>
				<UML:DataType xmi.id="eaxmiid3" name="boolean" visibility="private" isRoot="false" isLeaf="false" isAbstract="false"/>
				<UML:DataType xmi.id="eaxmiid1" name="char" visibility="private" isRoot="false" isLeaf="false" isAbstract="false"/>
				<UML:DataType xmi.id="eaxmiid2" name="long" visibility="private" isRoot="false" isLeaf="false" isAbstract="false"/>
				<UML:DataType xmi.id="eaxmiid0" name="int" visibility="private" isRoot="false" isLeaf="false" isAbstract="false"/>
			</UML:Namespace.ownedElement>
		</UML:Model>
		<UML:Diagram name="ont.MedMgr" xmi.id="EAID_CFC0CA38_C39A_4d59_9A58_65A6D8A84F93" diagramType="ClassDiagram" owner="EAPK_4DB1BF9B_A889_4442_BBDF_E0632A20E77C" toolName="Enterprise Architect 2.5">
			<UML:ModelElement.taggedValue>
				<UML:TaggedValue tag="version" value="1.0"/>
				<UML:TaggedValue tag="author" value="Venelin"/>
				<UML:TaggedValue tag="created_date" value="2012-01-27 14:49:05"/>
				<UML:TaggedValue tag="modified_date" value="2012-02-01 15:38:08"/>
				<UML:TaggedValue tag="package" value="EAPK_4DB1BF9B_A889_4442_BBDF_E0632A20E77C"/>
				<UML:TaggedValue tag="type" value="Logical"/>
				<UML:TaggedValue tag="swimlanes" value="locked=false;orientation=0;width=0;inbar=false;names=false;color=0;bold=false;fcol=0;;cls=0;"/>
				<UML:TaggedValue tag="matrixitems" value="locked=false;matrixactive=false;swimlanesactive=true;width=1;"/>
				<UML:TaggedValue tag="ea_localid" value="676"/>
				<UML:TaggedValue tag="EAStyle" value="ShowPrivate=1;ShowProtected=1;ShowPublic=1;HideRelationships=0;Locked=0;Border=1;HighlightForeign=1;PackageContents=1;SequenceNotes=0;ScalePrintImage=0;PPgs.cx=1;PPgs.cy=1;DocSize.cx=850;DocSize.cy=1098;ShowDetails=0;Orientation=P;Zoom=100;ShowTags=0;OpParams=1;VisibleAttributeDetail=0;ShowOpRetType=1;ShowIcons=1;CollabNums=0;HideProps=0;ShowReqs=0;ShowCons=0;PaperSize=1;HideParents=0;UseAlias=0;HideAtts=0;HideOps=0;HideStereo=0;HideElemStereo=0;ShowTests=0;ShowMaint=0;ConnectorNotation=UML 2.1;ExplicitNavigability=0;AdvancedElementProps=1;AdvancedFeatureProps=1;AdvancedConnectorProps=1;ShowNotes=0;SuppressBrackets=0;SuppConnectorLabels=0;PrintPageHeadFoot=0;ShowAsList=0;"/>
				<UML:TaggedValue tag="styleex" value="ExcludeRTF=0;DocAll=0;HideQuals=0;AttPkg=1;ShowTests=0;ShowMaint=0;SuppressFOC=1;MatrixActive=0;SwimlanesActive=1;MatrixLineWidth=1;MatrixLocked=0;TConnectorNotation=UML 2.1;TExplicitNavigability=0;AdvancedElementProps=1;AdvancedFeatureProps=1;AdvancedConnectorProps=1;ProfileData=;MDGDgm=;STBLDgm=;ShowNotes=0;VisibleAttributeDetail=0;ShowOpRetType=1;SuppressBrackets=0;SuppConnectorLabels=0;PrintPageHeadFoot=0;ShowAsList=0;"/>
			</UML:ModelElement.taggedValue>
			<UML:Diagram.element>
				<UML:DiagramElement geometry="Left=568;Top=677;Right=800;Bottom=778;" subject="EAID_CB5BDDFF_8D6E_44c1_9D57_CE51478C1DA9" seqno="1" style="DUID=56613301;"/>
				<UML:DiagramElement geometry="Left=621;Top=439;Right=747;Bottom=509;" subject="EAID_221369A4_8050_4b68_A7F0_9431AB359338" seqno="2" style="DUID=DF861E79;"/>
				<UML:DiagramElement geometry="Left=355;Top=439;Right=485;Bottom=509;" subject="EAID_7609610B_51A5_4b72_B7DD_DF4E35D63C6B" seqno="3" style="DUID=C7B8EEC8;"/>
				<UML:DiagramElement geometry="Left=38;Top=430;Right=220;Bottom=518;" subject="EAID_2FF07B53_DA18_4ab5_AAA5_BE8949C44933" seqno="4" style="DUID=53CBD102;"/>
				<UML:DiagramElement geometry="Left=34;Top=203;Right=224;Bottom=330;" subject="EAID_A043C0B5_1FD9_4a44_B5E0_4D9DFCBF4549" seqno="5" style="DUID=3620AEB8;"/>
				<UML:DiagramElement geometry="Left=611;Top=204;Right=757;Bottom=328;" subject="EAID_D6D1CDC5_3805_4209_BFDB_E29147C7C283" seqno="6" style="DUID=31CD5975;"/>
				<UML:DiagramElement geometry="Left=61;Top=677;Right=197;Bottom=765;" subject="EAID_DE6BB62E_6A29_4ab3_91E0_EFD6C851A4C0" seqno="7" style="DUID=297C9004;"/>
				<UML:DiagramElement geometry="Left=342;Top=231;Right=498;Bottom=301;" subject="EAID_07A78DEC_947E_4ba1_9743_E9A32521B4C8" seqno="8" style="DUID=E0CB3E77;"/>
				<UML:DiagramElement geometry="SX=0;SY=0;EX=0;EY=0;EDGE=1;$LLB=;LLT=;LMT=CX=88:CY=13:OX=0:OY=0:HDN=0:BLD=0:ITA=0:UND=0:CLR=-1:ALN=0:DIR=0:ROT=0;LMB=;LRT=;LRB=;IRHS=;ILHS=;Path=;" subject="EAID_03DE4CCF_482E_40ff_AEC5_20C0E762F233" style="Mode=3;EOID=DF861E79;SOID=56613301;Color=-1;LWidth=0;Hidden=0;"/>
				<UML:DiagramElement geometry="SX=0;SY=0;EX=0;EY=0;EDGE=1;$LLB=;LLT=;LMT=CX=60:CY=13:OX=0:OY=0:HDN=0:BLD=0:ITA=0:UND=0:CLR=-1:ALN=0:DIR=0:ROT=0;LMB=;LRT=;LRB=;IRHS=;ILHS=;Path=;" subject="EAID_56689A4B_2F1D_4206_BF9B_F318948A3CE1" style="Mode=3;EOID=53CBD102;SOID=297C9004;Color=-1;LWidth=0;Hidden=0;"/>
				<UML:DiagramElement geometry="SX=0;SY=0;EX=0;EY=0;EDGE=1;$LLB=;LLT=;LMT=CX=87:CY=13:OX=0:OY=0:HDN=0:BLD=0:ITA=0:UND=0:CLR=-1:ALN=0:DIR=0:ROT=0;LMB=;LRT=;LRB=;IRHS=;ILHS=;Path=;" subject="EAID_7D5A7D99_64CF_4654_A409_A14483D0B5C3" style="Mode=3;EOID=3620AEB8;SOID=53CBD102;Color=-1;LWidth=0;Hidden=0;"/>
				<UML:DiagramElement geometry="SX=0;SY=0;EX=0;EY=0;EDGE=1;$LLB=;LLT=;LMT=CX=67:CY=13:OX=0:OY=0:HDN=0:BLD=0:ITA=0:UND=0:CLR=-1:ALN=0:DIR=0:ROT=0;LMB=;LRT=;LRB=;IRHS=;ILHS=;Path=;" subject="EAID_905A7C67_88A0_43d3_BD7B_CEB2D162BB90" style="Mode=3;EOID=31CD5975;SOID=DF861E79;Color=-1;LWidth=0;Hidden=0;"/>
				<UML:DiagramElement geometry="SX=0;SY=0;EX=0;EY=0;EDGE=4;$LLB=CX=16:CY=13:OX=0:OY=0:HDN=0:BLD=0:ITA=0:UND=0:CLR=-1:ALN=0:DIR=0:ROT=0;LLT=;LMT=CX=48:CY=13:OX=0:OY=0:HDN=0:BLD=0:ITA=0:UND=0:CLR=-1:ALN=0:DIR=0:ROT=0;LMB=;LRT=;LRB=;IRHS=;ILHS=;Path=;" subject="EAID_FD5AD238_8F8B_4e62_A206_1E7967D3FFB4" style="Mode=3;EOID=E0CB3E77;SOID=31CD5975;Color=-1;LWidth=0;Hidden=0;"/>
				<UML:DiagramElement geometry="SX=0;SY=0;EX=0;EY=0;EDGE=2;$LLB=;LLT=;LMT=CX=75:CY=13:OX=0:OY=0:HDN=0:BLD=0:ITA=0:UND=0:CLR=-1:ALN=0:DIR=0:ROT=0;LMB=;LRT=;LRB=;IRHS=;ILHS=;Path=;" subject="EAID_AA3427EF_C860_41b3_830C_97A0EDA98B63" style="Mode=3;EOID=E0CB3E77;SOID=3620AEB8;Color=-1;LWidth=0;Hidden=0;"/>
				<UML:DiagramElement geometry="SX=0;SY=0;EX=0;EY=0;EDGE=1;$LLB=;LLT=;LMT=CX=71:CY=13:OX=0:OY=0:HDN=0:BLD=0:ITA=0:UND=0:CLR=-1:ALN=0:DIR=0:ROT=0;LMB=;LRT=;LRB=;IRHS=;ILHS=;Path=;" subject="EAID_3B315DD9_BBA8_4b3e_A2B7_9C4C530D7D44" style="Mode=3;EOID=E0CB3E77;SOID=C7B8EEC8;Color=-1;LWidth=0;Hidden=0;"/>
			</UML:Diagram.element>
		</UML:Diagram>
	</XMI.content>
	<XMI.difference/>
	<XMI.extensions xmi.extender="Enterprise Architect 2.5">
		<EAStub xmi.id="EAID_0695D040_8E2F_4b8a_97B8_8D5409F6D124" name="Medical doctor" UMLType="Actor"/>
		<EAStub xmi.id="EAID_1985356A_6E50_4781_9DF9_EA92F3AA0BCD" name="Pill dispenser" UMLType="Actor"/>
	</XMI.extensions>
</XMI>
