<?xml version="1.0" encoding="windows-1252"?>
<XMI xmi.version="1.1" xmlns:UML="omg.org/UML1.3">
	<XMI.header>
		<XMI.documentation>
			<XMI.exporter>Enterprise Architect</XMI.exporter>
			<XMI.exporterVersion>2.5</XMI.exporterVersion>
		</XMI.documentation>
	</XMI.header>
	<XMI.content>
		<UML:Model name="EA Model" xmi.id="MX_EAID_4673EB53_9AF3_46d6_9285_725EE2E43C36">
			<UML:Namespace.ownedElement>
				<UML:Class name="EARootClass" xmi.id="EAID_11111111_5487_4080_A7F4_41526CB0AA00" isRoot="true" isLeaf="false" isAbstract="false"/>
				<UML:Package name="Naming" xmi.id="EAPK_4673EB53_9AF3_46d6_9285_725EE2E43C36" isRoot="false" isLeaf="false" isAbstract="false" visibility="public">
					<UML:ModelElement.taggedValue>
						<UML:TaggedValue tag="parent" value="EAPK_9B3DD1F9_6EF6_4391_8288_539272860530"/>
						<UML:TaggedValue tag="created" value="2010-06-07 14:04:01"/>
						<UML:TaggedValue tag="modified" value="2010-06-07 14:04:01"/>
						<UML:TaggedValue tag="iscontrolled" value="TRUE"/>
						<UML:TaggedValue tag="xmlpath" value="ea7\725EE2E43C36.xml"/>
						<UML:TaggedValue tag="version" value="1.0"/>
						<UML:TaggedValue tag="isprotected" value="FALSE"/>
						<UML:TaggedValue tag="usedtd" value="FALSE"/>
						<UML:TaggedValue tag="logxml" value="FALSE"/>
						<UML:TaggedValue tag="packageFlags" value="VCCFG=uAAL;CRC=0;"/>
						<UML:TaggedValue tag="phase" value="1.0"/>
						<UML:TaggedValue tag="status" value="Proposed"/>
						<UML:TaggedValue tag="author" value="Requirement Taskforce"/>
						<UML:TaggedValue tag="alias" value="R2.2.10"/>
						<UML:TaggedValue tag="complexity" value="1"/>
						<UML:TaggedValue tag="ea_stype" value="Public"/>
						<UML:TaggedValue tag="tpos" value="0"/>
						<UML:TaggedValue tag="gentype" value="Java"/>
					</UML:ModelElement.taggedValue>
					<UML:Namespace.ownedElement>
						<UML:Collaboration xmi.id="EAID_4673EB53_9AF3_46d6_9285_725EE2E43C36_Collaboration" name="Collaborations">
							<UML:Namespace.ownedElement>
								<UML:ClassifierRole name="Separate namespaces" xmi.id="EAID_55E4A290_1A84_421b_95B5_37480EF50456" visibility="public" base="EAID_11111111_5487_4080_A7F4_41526CB0AA00">
									<UML:ModelElement.stereotype>
										<UML:Stereotype name="Functional"/>
									</UML:ModelElement.stereotype>
									<UML:ModelElement.taggedValue>
										<UML:TaggedValue tag="documentation" value="&lt;b&gt;Description&lt;/b&gt;&#xA;The identification of subsystems shall be unique, but uniform.&#xA;&lt;b&gt;Measure to check&lt;/b&gt;&#xA;Each subsystem has its own namespace and can be uniquely identified.&#xA;&lt;b&gt;Rationale&lt;/b&gt;&#xA;The development of distributed subsystems is easier with separate and unique namespaces.&#xA;&lt;b&gt;Reference&lt;/b&gt;&#xA;GENESYS R2.2.10.1, R2.2.10.2&#xA;&lt;b&gt;WP:&lt;/b&gt; 1,2,4&#xA;&lt;b&gt;Ranking:&lt;/b&gt; 5"/>
										<UML:TaggedValue tag="isAbstract" value="false"/>
										<UML:TaggedValue tag="isSpecification" value="false"/>
										<UML:TaggedValue tag="ea_stype" value="Requirement"/>
										<UML:TaggedValue tag="ea_ntype" value="0"/>
										<UML:TaggedValue tag="version" value="1.0"/>
										<UML:TaggedValue tag="package" value="EAPK_4673EB53_9AF3_46d6_9285_725EE2E43C36"/>
										<UML:TaggedValue tag="date_created" value="2010-06-07 14:04:11"/>
										<UML:TaggedValue tag="date_modified" value="2010-06-07 14:04:11"/>
										<UML:TaggedValue tag="gentype" value="&lt;none&gt;"/>
										<UML:TaggedValue tag="tagged" value="0"/>
										<UML:TaggedValue tag="package_name" value="Naming"/>
										<UML:TaggedValue tag="phase" value="1.0"/>
										<UML:TaggedValue tag="alias" value="R2.2.10.1"/>
										<UML:TaggedValue tag="author" value="Requirement Taskforce"/>
										<UML:TaggedValue tag="complexity" value="1"/>
										<UML:TaggedValue tag="status" value="Proposed"/>
										<UML:TaggedValue tag="stereotype" value="Functional"/>
										<UML:TaggedValue tag="tpos" value="0"/>
										<UML:TaggedValue tag="keywords" value="WP1 WP2 WP4"/>
										<UML:TaggedValue tag="ea_localid" value="1518"/>
										<UML:TaggedValue tag="ea_eleType" value="element"/>
										<UML:TaggedValue tag="difficulty" value="Medium"/>
										<UML:TaggedValue tag="priority" value="High"/>
										<UML:TaggedValue tag="style" value="BackColor=-1;BorderColor=-1;BorderWidth=-1;FontColor=-1;VSwimLanes=1;HSwimLanes=1;BorderStyle=0;"/>
										<UML:TaggedValue tag="$ea_xref_property" value="$XREFPROP=$XID={6ECD88EF-84AB-446f-BDC1-42BBD430296E}$XID;$NAM=Stereotypes$NAM;$TYP=element property$TYP;$VIS=Public$VIS;$PAR=0$PAR;$DES=@STEREO;Name=Functional;GUID={C3354BB0-6AE7-4800-B99A-832932003762};@ENDSTEREO;$DES;$CLT={55E4A290-1A84-421b-95B5-37480EF50456}$CLT;$SUP=&lt;none&gt;$SUP;$ENDXREF;"/>
									</UML:ModelElement.taggedValue>
								</UML:ClassifierRole>
							</UML:Namespace.ownedElement>
							<UML:Collaboration.interaction/>
						</UML:Collaboration>
					</UML:Namespace.ownedElement>
				</UML:Package>
			</UML:Namespace.ownedElement>
		</UML:Model>
	</XMI.content>
	<XMI.difference/>
	<XMI.extensions xmi.extender="Enterprise Architect 2.5"/>
</XMI>
